{
  "date": "2026-01-24",
  "newsInfo": [
    {
      "link": "https://tw.news.yahoo.com/%E6%9C%80%E7%BE%8Ej%E5%A5%B3%E9%83%8E%E6%98%AF%E5%A5%B9-%E6%9B%BE%E6%84%B7%E7%8E%B9%E7%BD%95%E9%9C%B2%E9%9D%A2%E7%AB%9F%E8%A2%AB%E5%95%8F-%E6%98%AF%E8%AA%B0-%E8%80%81%E7%B2%89%E5%98%86-%E6%99%82%E4%BB%A3%E8%AE%8A%E4%BA%86-071000063.html",
      "headLine": "最美J女郎是她！曾愷玹罕露面竟被問「是誰？」老粉嘆：時代變了",
      "publishDate": "2026-01-24T07:10:00.000Z",
      "source": "{\"@context\":\"http://schema.org\",\"@type\":\"NewsArticle\",\"mainEntityOfPage\":\"https://tw.news.yahoo.com/%E6%9C%80%E7%BE%8Ej%E5%A5%B3%E9%83%8E%E6%98%AF%E5%A5%B9-%E6%9B%BE%E6%84%B7%E7%8E%B9%E7%BD%95%E9%9C%B2%E9%9D%A2%E7%AB%9F%E8%A2%AB%E5%95%8F-%E6%98%AF%E8%AA%B0-%E8%80%81%E7%B2%89%E5%98%86-%E6%99%82%E4%BB%A3%E8%AE%8A%E4%BA%86-071000063.html\",\"headline\":\"最美J女郎是她！曾愷玹罕露面竟被問「是誰？」老粉嘆：時代變了\",\"datePublished\":\"2026-01-24T07:10:00.000Z\",\"dateModified\":\"2026-01-24T07:10:00.000Z\",\"keywords\":[\"曾愷玹\"],\"description\":\"41歲女星曾愷玹，有著「最美J女郎」稱號，2013年與圈外男友步入婚姻後，將生活重心放在家庭，逐漸淡出螢光幕。近來透過票房破億電影《陽光女子合唱團》，再度引起討論，久違露面，女神狀態曝光。記者林汝珊\",\"publisher\":{\"@type\":\"Organization\",\"name\":\"Yahoo奇摩新聞\",\"logo\":{\"@type\":\"ImageObject\",\"url\":\"https://s.yimg.com/cv/apiv2/twmobi/icon/yahoo_tw_logo_structuredata_20200630.png\",\"width\":136,\"height\":60}},\"author\":{\"@type\":\"Person\",\"name\":\"三立新聞網\",\"url\":\"\",\"jobTitle\":\"\"},\"creator\":{\"@type\":\"Person\",\"name\":\"三立新聞網\",\"url\":\"\",\"jobTitle\":\"\"},\"provider\":{\"@type\":\"Organization\",\"name\":\"三立新聞網 setn.com\",\"url\":\"http://www.setn.com/\",\"logo\":{\"@type\":\"ImageObject\",\"width\":316,\"height\":48,\"url\":\"https://s.yimg.com/os/creatr-uploaded-images/2025-01/2c15e170-d866-11ef-97ff-6019437716ae\"}},\"image\":{\"@type\":\"ImageObject\",\"url\":\"https://s.yimg.com/ny/api/res/1.2/3dA73XtuBjRhD6vvsUB1mw--/YXBwaWQ9aGlnaGxhbmRlcjt3PTcwNTtoPTEwMDM-/https://media.zenfs.com/ko/setn.com.tw/675ece569d77ab35c310ddde5df72ad8\",\"height\":673,\"width\":473},\"thumbnailUrl\":\"https://s.yimg.com/ny/api/res/1.2/3dA73XtuBjRhD6vvsUB1mw--/YXBwaWQ9aGlnaGxhbmRlcjt3PTcwNTtoPTEwMDM-/https://media.zenfs.com/ko/setn.com.tw/675ece569d77ab35c310ddde5df72ad8\"}",
      "content": "記者林汝珊／台北報導曾愷玹被封為「最美J女郎」。（圖／翻攝自IG）41歲女星曾愷玹，有著「最美J女郎」稱號，2013年與圈外男友步入婚姻後，將生活重心放在家庭，逐漸淡出螢光幕。近來透過票房破億電影《陽光女子合唱團》，再度引起討論，久違露面，女神狀態曝光。曾愷玹外型清新、氣質出眾，早期曾擔任多部MV女主角，曾在周杰倫的MV《我不配》飾演女主角，並在電影中《不能說的秘密》飾演女配角，被外界封為「最美J女郎」。曾愷玹近來出演電影《陽光女子合唱團》。（圖／翻攝自IG）曾愷玹近來在《陽光女子合唱團》演出，透過Threads分享心情：「這部電影讓我一次擁有兩個女兒。」她感性表示，每個角色都有各自的故事，每一份愛都獨一無二，希望這部充滿音樂與情感的作品，能帶給觀眾溫柔的療癒力量。廣告廣告粉絲留言區瞬間湧入回憶殺，「在大銀幕看到仙女真的太驚喜了」、「我可以預約下輩子當女兒嗎？」不過也有年輕觀眾一臉困惑「她是誰？」讓不少老粉忍不住感嘆：「竟然到了還要介紹曾愷玹的時代了。」更多三立新聞網報導車銀優完了？驚爆逃漏稅200億 法律界揭「1關鍵」恐遭判5年59歲美魔女山上脫了！「僅剩Bra上下抖動」手腳凍傷 崩潰：我好冷車銀優爆逃稅200億！「遭疑說謊」力挺父母餐廳 網不滿：真的很噁心霍諾德攀101遇雨延期！網友炸鍋怒嗆「會怕別爬」本尊83字回應了",
      "imageUrl": "https://s.yimg.com/ny/api/res/1.2/3dA73XtuBjRhD6vvsUB1mw--/YXBwaWQ9aGlnaGxhbmRlcjt3PTcwNTtoPTEwMDM-/https://media.zenfs.com/ko/setn.com.tw/675ece569d77ab35c310ddde5df72ad8",
      "imageProvider": "曾愷玹被封為「最美J女郎」。（圖／翻攝自IG）",
      "authorName": "三立新聞網",
      "newsProvider": "三立新聞網 setn.com",
      "suggestLine": "好的，這則新聞的引導式句子，請參考以下 4 句：\n\n1.  J女郎回歸！\n2.  她，你還記得嗎？\n3.  41歲神凍齡！\n4.  昔日女神，今又現身？"
    },
    {
      "link": "https://tw.news.yahoo.com/%E8%81%BD%E8%AA%AA%E4%BD%A0%E8%A6%81%E7%88%AC%E5%8F%B0%E5%8C%97101-%E5%A5%A7%E6%96%AF%E5%8D%A1%E5%BD%B1%E5%90%8E%E7%AA%81%E5%90%91%E9%9C%8D%E8%AB%BE%E5%BE%B7%E4%B8%8B%E6%88%B0%E5%B8%96-%E6%A4%85%E5%AD%90%E6%94%80%E5%B2%A9-%E5%A4%AA%E9%A9%9A%E4%BA%BA-075300113.html",
      "headLine": "聽說你要爬台北101！奧斯卡影后突向霍諾德下戰帖 「椅子攀岩」太驚人",
      "publishDate": "2026-01-24T07:53:00.000Z",
      "source": "{\"@context\":\"http://schema.org\",\"@type\":\"NewsArticle\",\"mainEntityOfPage\":\"https://tw.news.yahoo.com/%E8%81%BD%E8%AA%AA%E4%BD%A0%E8%A6%81%E7%88%AC%E5%8F%B0%E5%8C%97101-%E5%A5%A7%E6%96%AF%E5%8D%A1%E5%BD%B1%E5%90%8E%E7%AA%81%E5%90%91%E9%9C%8D%E8%AB%BE%E5%BE%B7%E4%B8%8B%E6%88%B0%E5%B8%96-%E6%A4%85%E5%AD%90%E6%94%80%E5%B2%A9-%E5%A4%AA%E9%A9%9A%E4%BA%BA-075300113.html\",\"headline\":\"聽說你要爬台北101！奧斯卡影后突向霍諾德下戰帖 「椅子攀岩」太驚人\",\"datePublished\":\"2026-01-24T07:53:00.000Z\",\"dateModified\":\"2026-01-24T07:53:00.000Z\",\"keywords\":[\"霍諾德\",\"莎莉賽隆\",\"攀岩\"],\"description\":\"美國攀岩大神霍諾德(Alex Honnold)原訂今（24日）挑戰徒手攀登台北101，不過因為天候不佳而延期至明（25日）上午9點，仍讓許多網友期待表現。有趣的是，奧斯卡影后莎莉賽隆（Charlize Theron）得知霍諾德要進行的挑戰後，竟無預警向對方下戰帖，以「椅子攀岩」的方式一決高下。蔡佩伶報導\",\"publisher\":{\"@type\":\"Organization\",\"name\":\"Yahoo奇摩新聞\",\"logo\":{\"@type\":\"ImageObject\",\"url\":\"https://s.yimg.com/cv/apiv2/twmobi/icon/yahoo_tw_logo_structuredata_20200630.png\",\"width\":136,\"height\":60}},\"author\":{\"@type\":\"Person\",\"name\":\"三立新聞網\",\"url\":\"\",\"jobTitle\":\"\"},\"creator\":{\"@type\":\"Person\",\"name\":\"三立新聞網\",\"url\":\"\",\"jobTitle\":\"\"},\"provider\":{\"@type\":\"Organization\",\"name\":\"三立新聞網 setn.com\",\"url\":\"http://www.setn.com/\",\"logo\":{\"@type\":\"ImageObject\",\"width\":316,\"height\":48,\"url\":\"https://s.yimg.com/os/creatr-uploaded-images/2025-01/2c15e170-d866-11ef-97ff-6019437716ae\"}},\"image\":{\"@type\":\"ImageObject\",\"url\":\"https://s.yimg.com/ny/api/res/1.2/3PSjej2gErQVGrxn9iswLw--/YXBwaWQ9aGlnaGxhbmRlcjt3PTI0MDA7aD0xMzUw/https://media.zenfs.com/ko/setn.com.tw/502a63ec97c5f4f3bda3ae07864a9017\",\"height\":675,\"width\":1200},\"thumbnailUrl\":\"https://s.yimg.com/ny/api/res/1.2/3PSjej2gErQVGrxn9iswLw--/YXBwaWQ9aGlnaGxhbmRlcjt3PTI0MDA7aD0xMzUw/https://media.zenfs.com/ko/setn.com.tw/502a63ec97c5f4f3bda3ae07864a9017\"}",
      "content": "娛樂中心／蔡佩伶報導莎莉賽隆率先進行「椅子攀岩」挑戰。（圖／翻攝自IG）美國攀岩大神霍諾德(Alex Honnold)原訂今（24日）挑戰徒手攀登台北101，不過因為天候不佳而延期至明（25日）上午9點，讓許多網友期待表現。有趣的是，奧斯卡影后莎莉賽隆（Charlize Theron）得知霍諾德要進行的挑戰後，竟無預警向對方下戰帖，以「椅子攀岩」的方式一決高下。從曝光的畫面可以看到，莎莉賽隆表示聽聞霍諾德要爬101，正巧自己因為電影也有進行攀岩訓練，於是喊話霍諾德可以利用家中物品來挑戰，最終，莎莉賽隆率先使用椅子展示攀岩的技術，輪到霍諾德時，他也利用椅子完成挑戰。廣告廣告只見霍諾德先是坐在椅子上，隨後便開始攀爬，過程中椅子雖然一度險些倒下，不過霍諾德利用核心力量穩定住椅子，成功爬過去，兩人精彩表現皆吸引7萬多名網友按讚朝聖。霍諾德成功完成挑戰。（圖／翻攝自IG）更多三立新聞網報導病毒源頭是老公！女星2女兒同時送急診打點滴 心疼洩最新病況爆乳主持尾牙！蔡尚樺「階梯慘跌」畫面流出 蕭煌奇、阿Ken一招救場霍建華吃飯被認出！他霸氣出手替粉絲「整桌買單」 女學生激動道謝停更動畫一年！百萬插畫家突公開「脫褲開腿片」 網看了全嚇壞",
      "imageUrl": "https://s.yimg.com/ny/api/res/1.2/xQF4aeevF7u2.3bh9y6qnw--/YXBwaWQ9aGlnaGxhbmRlcjt3PTk2MDtoPTU0MA--/https://media.zenfs.com/ko/setn.com.tw/502a63ec97c5f4f3bda3ae07864a9017",
      "imageProvider": "莎莉賽隆率先進行「椅子攀岩」挑戰。（圖／翻攝自IG）",
      "authorName": "三立新聞網",
      "newsProvider": "三立新聞網 setn.com",
      "suggestLine": "1. 影后「椅」外挑戰！\n2. 莎莉賽隆：爬椅子才過癮！\n3. 攀岩神「椅」外被KO？\n4. 影后戰攀岩王，道具是椅子！"
    },
    {
      "link": "https://tw.news.yahoo.com/%E5%A9%9A%E7%A6%AE%E5%80%92%E6%95%B8-%E5%A4%A9-lulu-%E6%97%A9%E6%94%B6%E9%83%81%E6%96%B9%E5%A4%AB%E5%A9%A6%E7%8F%A0%E5%AF%B6%E6%96%B0%E5%A9%9A%E7%A6%AE-%E7%9B%B4%E5%91%BC%E5%A4%AA%E5%B9%B8%E7%A6%8F-062000242.html",
      "headLine": "婚禮倒數一天！Lulu一早收郁方夫婦珠寶新婚禮 直呼太幸福",
      "publishDate": "2026-01-24T06:20:00.000Z",
      "source": "{\"@context\":\"http://schema.org\",\"@type\":\"NewsArticle\",\"mainEntityOfPage\":\"https://tw.news.yahoo.com/%E5%A9%9A%E7%A6%AE%E5%80%92%E6%95%B8-%E5%A4%A9-lulu-%E6%97%A9%E6%94%B6%E9%83%81%E6%96%B9%E5%A4%AB%E5%A9%A6%E7%8F%A0%E5%AF%B6%E6%96%B0%E5%A9%9A%E7%A6%AE-%E7%9B%B4%E5%91%BC%E5%A4%AA%E5%B9%B8%E7%A6%8F-062000242.html\",\"headline\":\"婚禮倒數一天！Lulu一早收郁方夫婦珠寶新婚禮 直呼太幸福\",\"datePublished\":\"2026-01-24T06:20:00.000Z\",\"dateModified\":\"2026-01-24T06:20:00.000Z\",\"keywords\":[\"陳漢典\",\"Lulu\",\"台北文華東方酒店\",\"FTNN新聞網\",\"郁方\"],\"description\":\"[FTNN新聞網]實習記者王保伶／綜合報導藝人Lulu（黃路梓茵）與陳漢典明（25）日將於台北文華東方酒店舉辦婚禮，Lulu今（24）日在社群平台曬出一張合照，透露...\",\"publisher\":{\"@type\":\"Organization\",\"name\":\"Yahoo奇摩新聞\",\"logo\":{\"@type\":\"ImageObject\",\"url\":\"https://s.yimg.com/cv/apiv2/twmobi/icon/yahoo_tw_logo_structuredata_20200630.png\",\"width\":136,\"height\":60}},\"author\":{\"@type\":\"Person\",\"name\":\"FTNN新聞網\",\"url\":\"\",\"jobTitle\":\"\"},\"creator\":{\"@type\":\"Person\",\"name\":\"FTNN新聞網\",\"url\":\"\",\"jobTitle\":\"\"},\"provider\":{\"@type\":\"Organization\",\"name\":\"FTNN新聞網\",\"url\":\"https://www.ftnn.com.tw/\",\"logo\":{\"@type\":\"ImageObject\",\"width\":566,\"height\":100,\"url\":\"https://s.yimg.com/os/creatr-uploaded-images/2023-05/4c170630-ff4f-11ed-af3f-ab9265c8f46c\"}},\"image\":{\"@type\":\"ImageObject\",\"url\":\"https://s.yimg.com/ny/api/res/1.2/CZYFlRrBRKjXWpS9iBD0CA--/YXBwaWQ9aGlnaGxhbmRlcjt3PTIzOTg7aD0xMzU0/https://media.zenfs.com/zh-tw/ftnn_com_tw_939/143733e8676ca386c6339a652c4f5c4a\",\"height\":677,\"width\":1199},\"thumbnailUrl\":\"https://s.yimg.com/ny/api/res/1.2/CZYFlRrBRKjXWpS9iBD0CA--/YXBwaWQ9aGlnaGxhbmRlcjt3PTIzOTg7aD0xMzU0/https://media.zenfs.com/zh-tw/ftnn_com_tw_939/143733e8676ca386c6339a652c4f5c4a\"}",
      "content": "[FTNN新聞網]實習記者王保伶／綜合報導藝人Lulu（黃路梓茵）與陳漢典明（25）日將於台北文華東方酒店舉辦婚禮，Lulu今（24）日在社群平台曬出一張合照，透露收到來自郁方夫妻的新婚大禮，直呼相當感動，溫馨互動引發網友關注與祝福。Lulu今日在社群平台曬出一張合照，透露收到來自郁方夫妻的新婚大禮。（圖／翻攝Lulu 黃路梓茵、好門媳婦的秘密生活郁小方臉書）Lulu今（24）日在臉書分享一張溫馨合照，照片中，Lulu與老公陳漢典兩人面露微笑，藝人郁方與「斐儷珠寶」總經理陳昱羲（Steven）夫妻一同入鏡，Lulu手中拿著印有「斐儷珠寶」字樣的深綠色禮袋，寫道：「不可能一大早獲得一個來自斐儷珠寶的新婚大禮，還是Steven哥跟郁方姐親送，已經是太感動了！！！！我們太幸福了，有一群這麼愛我們的哥哥姐姐～」。廣告廣告郁方也發文分享，因為Lulu姓黃，因此選擇送黃鑽，希望Lulu平常日子可以方便佩戴，她也透露，先生特別交代不能送太大顆的鑽石，留點空間讓陳漢典之後有表現的機會。貼文曝光後，許多網友直呼「好人緣的兩位！祝幸福美滿長長久久」、「你們這一對太可愛太幸福，各位哥哥姐姐忍不住要疼你們」。Lulu與陳漢典的婚禮將於明（25）日登場，婚前陸續收到圈內好友祝福，也讓外界更加期待兩人的浪漫婚禮。更多FTNN新聞網報導Lulu夫妻保養之道！曝幫陳漢典加強這部位清潔 「直男真的比較大而化之」陳漢典、Lulu富士山絕美婚紗照曝光！偷藏「幸福密碼」 甜蜜告白閃瞎人陳漢典、Lulu高雄跨年合體主持 許願「跨完年手牽手一起吃宵夜」",
      "imageUrl": "https://s.yimg.com/ny/api/res/1.2/REdKUjbBP3aXIfedihFKBQ--/YXBwaWQ9aGlnaGxhbmRlcjt3PTk2MDtoPTU0Mg--/https://media.zenfs.com/zh-tw/ftnn_com_tw_939/143733e8676ca386c6339a652c4f5c4a",
      "imageProvider": "Lulu今日在社群平台曬出一張合照，透露收到來自郁方夫妻的新婚大禮。（圖／翻攝Lulu 黃路梓茵、好門媳婦的秘密生活郁小方臉書）",
      "authorName": "FTNN新聞網",
      "newsProvider": "FTNN新聞網",
      "suggestLine": "1. Lulu婚禮前收鑽石！\n2. 郁方送Lulu黃鑽！\n3. 大禮加持！Lulu婚閃！\n4. 豪門送禮！Lulu感動！"
    },
    {
      "link": "https://tw.news.yahoo.com/%E6%81%90%E6%88%90%E5%8D%97%E9%9F%93%E5%8F%B2%E4%B8%8A%E6%9C%80%E9%AB%98-%E8%BB%8A%E9%8A%80%E5%84%AA200%E5%84%84%E7%A8%85%E5%8B%99%E9%81%AD%E8%A8%8E-%E5%B1%AC%E5%AF%A6%E5%8F%AF%E5%85%A5%E5%85%A8%E7%90%83%E6%BC%94%E8%97%9D%E5%9C%88%E6%8E%92%E5%90%8D%E7%AC%AC7%E4%BD%8D-080200513.html",
      "headLine": "恐成南韓史上最高！車銀優200億稅務遭討 屬實可入全球演藝圈排名第7位",
      "publishDate": "2026-01-24T08:02:00.000Z",
      "source": "{\"@context\":\"http://schema.org\",\"@type\":\"NewsArticle\",\"mainEntityOfPage\":\"https://tw.news.yahoo.com/%E6%81%90%E6%88%90%E5%8D%97%E9%9F%93%E5%8F%B2%E4%B8%8A%E6%9C%80%E9%AB%98-%E8%BB%8A%E9%8A%80%E5%84%AA200%E5%84%84%E7%A8%85%E5%8B%99%E9%81%AD%E8%A8%8E-%E5%B1%AC%E5%AF%A6%E5%8F%AF%E5%85%A5%E5%85%A8%E7%90%83%E6%BC%94%E8%97%9D%E5%9C%88%E6%8E%92%E5%90%8D%E7%AC%AC7%E4%BD%8D-080200513.html\",\"headline\":\"恐成南韓史上最高！車銀優200億稅務遭討 屬實可入全球演藝圈排名第7位\",\"datePublished\":\"2026-01-24T08:02:00.000Z\",\"dateModified\":\"2026-01-24T08:02:00.000Z\",\"keywords\":[\"南韓國稅廳\",\"韓元\"],\"description\":\"南韓男團ASTRO成員，同時還有「臉蛋天才」之稱，目前正在服兵役的知名男星車銀優近日捲入高額稅務爭議，傳出遭南韓國稅廳通知補繳超過200億韓元（約新台幣4.3億元）所得稅，引發娛樂圈震撼。若國稅廳最終認定金額屬實，規模不僅將成為南韓演藝圈史上最高，也可能擠進全球藝人稅務追繳排名中第7名位置。\",\"publisher\":{\"@type\":\"Organization\",\"name\":\"Yahoo奇摩新聞\",\"logo\":{\"@type\":\"ImageObject\",\"url\":\"https://s.yimg.com/cv/apiv2/twmobi/icon/yahoo_tw_logo_structuredata_20200630.png\",\"width\":136,\"height\":60}},\"author\":{\"@type\":\"Person\",\"name\":\"三立新聞網\",\"url\":\"\",\"jobTitle\":\"\"},\"creator\":{\"@type\":\"Person\",\"name\":\"三立新聞網\",\"url\":\"\",\"jobTitle\":\"\"},\"provider\":{\"@type\":\"Organization\",\"name\":\"三立新聞網 setn.com\",\"url\":\"http://www.setn.com/\",\"logo\":{\"@type\":\"ImageObject\",\"width\":316,\"height\":48,\"url\":\"https://s.yimg.com/os/creatr-uploaded-images/2025-01/2c15e170-d866-11ef-97ff-6019437716ae\"}},\"image\":{\"@type\":\"ImageObject\",\"url\":\"https://s.yimg.com/ny/api/res/1.2/x0PpI61AMlNOuQS_FbSzZg--/YXBwaWQ9aGlnaGxhbmRlcjt3PTcwNTtoPTM5Nw--/https://media.zenfs.com/ko/setn.com.tw/07859989ff290d9fb21d82b2621cfb47\",\"height\":224,\"width\":398},\"thumbnailUrl\":\"https://s.yimg.com/ny/api/res/1.2/x0PpI61AMlNOuQS_FbSzZg--/YXBwaWQ9aGlnaGxhbmRlcjt3PTcwNTtoPTM5Nw--/https://media.zenfs.com/ko/setn.com.tw/07859989ff290d9fb21d82b2621cfb47\"}",
      "content": "記者蒲世芸／綜合報導南韓男團ASTRO成員，同時還有「臉蛋天才」之稱，目前正在服兵役的知名男星車銀優近日捲入高額稅務爭議，傳出遭南韓國稅廳通知補繳超過200億韓元（約新台幣4.3億元）所得稅，引發娛樂圈震撼。若國稅廳最終認定金額屬實，規模不僅將成為南韓演藝圈史上最高，也可能擠進全球藝人稅務追繳排名中第7名位置。車銀優有臉蛋天才之稱。（圖／翻攝自IG @eunwo.o_c）恐入圍全球演藝圈逃稅大戶前段班根據《韓國經濟》23日報導，對於相關稅務爭議，車銀優方面回應，相關金額「尚未確定，也未正式告知」。然而，若車銀優最終確認為逃稅2百億韓元屬實，那他也將登上全球演藝圈的前十大排行榜中，並位居第7名。廣告廣告前六名分別為中國演員范冰冰（1440億韓元）、中國演員鄭爽（540億韓元）、足球明星C羅（240億韓元）、美國演員衛斯理史奈普（230億韓元）、美國音樂家威利尼爾森（220億韓元）、中國演員鄧倫（206億韓元）。至於原在榜單中排在車銀優前一名的拉丁天后夏奇拉，最初被追討約204億韓元稅款，但她在2023年與西班牙巴塞隆納法院達成協議，最終僅繳納約103億韓元罰金結案。上榜者中，中國藝人就占了3人。另外，還有足球天王梅西則是在2013年與父親捲入逃漏稅爭議，補繳約72億韓元，並於2016年遭西班牙法院判處約25億韓元罰金。若金額屬實，為南韓「壓倒性第一」若其200億韓元追繳金額確定，車銀優將成為南韓演藝圈「壓倒性第一」的稅務爭議案例。過去曾遭追稅的藝人，包括演員柳演錫（約70億韓元）、演員李荷妮（約60億韓元）、出演《信號》的影帝趙震雄（約11億韓元）、演員李準基（約9億韓元）、前天團JYJ成員朴有天（約4億韓元）等。不過，由於車銀優方面已表態將積極說明，外界也關注，未來是否會出現金額或認定上的變化。對於稅務風暴，車銀優方面表示將積極配合，與進行相關說明。（圖／翻攝自IG @eunwo.o_c）韓國稅廳盯上「家族法人」結構報導指出，過去藝人稅務爭議多半涉及漏報活動費、出演費，或隱匿現金收入；但近年爭議焦點，逐漸轉向一人企劃公司、家族名下法人、肖像權與廣告收益移轉等稅務認定問題。國稅廳此次對車銀優案的判斷，也正是基於這類結構。國稅廳認為，車銀優與其母親設立的法人簽署經紀相關服務合約，藉此適用低於個人所得稅率的法人稅率。依南韓國稅廳說法，車銀優的收入由所屬經紀公司Fantagio、A公司以及車銀優本人分配，但國稅廳認定，A公司「並未實際提供服務」，屬於紙上公司。據悉，A公司為車銀優母親所設立，初期登記地址位於仁川江華郡，該處正是車銀優父母經營的鰻魚餐廳所在地，也因擺放車銀優親筆簽名與照片，而為粉絲熟知。掌握全球脈動、深入觀點分析，訂閱一鍵看世界SET Global更多三立新聞網報導韓酷澎個資外洩成韓美政治危機？國務總理親赴美訪范斯強調「韓美友好」路透曝歐學到重要一課！首正面抗川普成焦點 達沃斯論壇五大重點一次看怒吼ICE快滾！不畏明州零下29度5萬人走上街 神職人員跪地祈禱也遭逮搭一次要價近7千元！法國高鐵推新豪奢座位 因禁童遭罵爆稱在「歧視」",
      "imageUrl": "https://s.yimg.com/ny/api/res/1.2/x0PpI61AMlNOuQS_FbSzZg--/YXBwaWQ9aGlnaGxhbmRlcjt3PTcwNTtoPTM5Nw--/https://media.zenfs.com/ko/setn.com.tw/07859989ff290d9fb21d82b2621cfb47",
      "imageProvider": "車銀優有臉蛋天才之稱。（圖／翻攝自IG @eunwo.o_c）",
      "authorName": "三立新聞網",
      "newsProvider": "三立新聞網 setn.com",
      "suggestLine": "1. 車銀優爆天價稅單\n2. 臉蛋天才也逃稅？\n3. 史上最高！車銀優\n4. 200億！南韓藝界震撼"
    },
    {
      "link": "https://tw.news.yahoo.com/%E4%BB%96%E8%84%AB%E5%8C%97%E5%85%A8%E5%9B%A0%E9%80%99%E5%8F%B0%E7%81%A3%E5%A5%B3%E5%AD%A9-%E6%84%9B%E7%9A%84%E8%BF%AB%E9%99%8D-%E7%9C%9F%E4%BA%BA%E7%89%88%E4%B8%BB%E8%A7%92%E5%82%B3%E5%A5%87%E4%BA%BA%E7%94%9F%E8%AC%9D%E5%B9%95-%E5%A6%BB%E6%B7%9A%E5%B4%A9%E5%91%8A%E5%88%A5-075516052.html",
      "headLine": "他脫北全因這台灣女孩！「愛的迫降」真人版主角傳奇人生謝幕 妻淚崩告別",
      "publishDate": "2026-01-24T07:55:16.000Z",
      "source": "{\"@context\":\"http://schema.org\",\"@type\":\"NewsArticle\",\"mainEntityOfPage\":\"https://tw.news.yahoo.com/%E4%BB%96%E8%84%AB%E5%8C%97%E5%85%A8%E5%9B%A0%E9%80%99%E5%8F%B0%E7%81%A3%E5%A5%B3%E5%AD%A9-%E6%84%9B%E7%9A%84%E8%BF%AB%E9%99%8D-%E7%9C%9F%E4%BA%BA%E7%89%88%E4%B8%BB%E8%A7%92%E5%82%B3%E5%A5%87%E4%BA%BA%E7%94%9F%E8%AC%9D%E5%B9%95-%E5%A6%BB%E6%B7%9A%E5%B4%A9%E5%91%8A%E5%88%A5-075516052.html\",\"headline\":\"他脫北全因這台灣女孩！「愛的迫降」真人版主角傳奇人生謝幕 妻淚崩告別\",\"datePublished\":\"2026-01-24T07:55:16.000Z\",\"dateModified\":\"2026-01-24T07:55:16.000Z\",\"keywords\":[\"李昌壽\",\"陳鈴真\",\"Newtalk新聞\"],\"description\":\"[Newtalk新聞] 被譽為韓劇「愛的迫降」真人版主角的前北韓柔道國手李昌壽，驚傳因心臟病突發辭世，享年58歲。他的妻子、台灣柔道選手陳鈴真在臉書發布靈堂照片證實噩耗，並感謝各界祈福。這位曾是北韓備受推崇的體育英雄，當年為了跨國愛情毅然脫北，如今這段轟動國際體壇的傳奇故事畫下句點。 據《朝鮮日報》報導，李昌壽是...\",\"publisher\":{\"@type\":\"Organization\",\"name\":\"Yahoo奇摩新聞\",\"logo\":{\"@type\":\"ImageObject\",\"url\":\"https://s.yimg.com/cv/apiv2/twmobi/icon/yahoo_tw_logo_structuredata_20200630.png\",\"width\":136,\"height\":60}},\"author\":{\"@type\":\"Person\",\"name\":\"Newtalk新聞 |曾郡秋 綜合報導\",\"url\":\"\",\"jobTitle\":\"\"},\"creator\":{\"@type\":\"Person\",\"name\":\"Newtalk新聞 |曾郡秋 綜合報導\",\"url\":\"\",\"jobTitle\":\"\"},\"provider\":{\"@type\":\"Organization\",\"name\":\"新頭殼\",\"url\":\"http://newtalk.tw/\",\"logo\":{\"@type\":\"ImageObject\",\"width\":448,\"height\":98,\"url\":\"https://s.yimg.com/os/creatr-uploaded-images/2020-10/c3945eb0-0862-11eb-bfdf-7eee5cb1f347\"}},\"image\":{\"@type\":\"ImageObject\",\"url\":\"https://s.yimg.com/cv/apiv2/social/images/yahoo_default_logo-1200x1200.png\",\"width\":1200,\"height\":1200},\"thumbnailUrl\":\"https://s.yimg.com/cv/apiv2/social/images/yahoo_default_logo-1200x1200.png\"}",
      "content": "[Newtalk新聞] 被譽為韓劇「愛的迫降」真人版主角的前北韓柔道國手李昌壽，驚傳因心臟病突發辭世，享年58歲。他的妻子、台灣柔道選手陳鈴真在臉書發布靈堂照片證實噩耗，並感謝各界祈福。這位曾是北韓備受推崇的體育英雄，當年為了跨國愛情毅然脫北，如今這段轟動國際體壇的傳奇故事畫下句點。據《朝鮮日報》報導，李昌壽是因心臟病驟逝。陳鈴真在得知丈夫死訊後，悲痛寫下「送我最愛的丈夫一路好走，前往極樂世界」，並感謝南韓柔道界長官與選手的祈福。這段情緣始於1989年世界錦標賽，儘管語言不通，兩人仍在短暫相聚中墜入愛河，並相約隔年北京亞運再見，沒想到這份承諾竟改變了他的一生。廣告廣告出身平壤的李昌壽，年輕時實力備受肯定，穩坐國家頭號主將大位，甚至擁有個人立像，地位崇高。他在1980年代屢次奪冠，並在世界青年及成人賽事奪牌，若非北韓當年抵制1988年漢城奧運，外界普遍評估他極有希望站上奧運頒獎台。然而，這些榮耀卻在一場比賽後瞬間變調。促使他下定決心離開故鄉的導火線，是1990年的北京亞運。當時他一路過關斬將卻在決賽敗給南韓選手鄭勳，僅獲銀牌。沒想到返國後竟遭國家嚴厲懲處，被下放至煤礦場勞動改造。這份因一次落敗就遭受的羞辱，加上對遠方戀人的思念，讓他在隔年短暫復出時，意識到回國後的巨大風險，進而選擇在歐洲參賽返程途中，奔赴當時西德的南韓大使館尋求庇護。面對鏡頭，李昌壽當時不僅控訴國家辜負選手，更公開向陳鈴真示愛，震撼全亞洲。陳鈴真看到報導後，不顧外界反對飛往南韓，兩人迅速完婚，這段佳話雖美，卻也導致兩韓體育交流破局，北韓因此全面加強對運動員監控。這段為了愛情不惜賭上性命的叛逃過程，後來也被視為韓劇「愛的迫降」的靈感原型，如今隨著李昌壽辭世，留給世人無限追憶。查看原文更多Newtalk新聞報導基隆勇消詹能傑殉職 卓榮泰赴靈堂上香慰問家屬陳鏞基難忘30年前少棒交流賽 兒子對運動也感興趣",
      "imageUrl": null,
      "imageProvider": null,
      "authorName": "Newtalk新聞 |曾郡秋 綜合報導",
      "newsProvider": "新頭殼",
      "suggestLine": "1. 愛的迫降主角逝世！\n2. 為愛脫北，傳奇落幕。\n3. 柔道英雄，情緣永逝。\n4. 真愛降落，人生謝幕。"
    },
    {
      "link": "https://tw.news.yahoo.com/%E8%BB%8A%E9%8A%80%E5%84%AA%E7%88%86%E8%B3%BA%E5%8D%83%E5%84%84%E5%8D%BB%E9%80%83%E7%A8%85-d%E7%A4%BE-%E7%9B%B4%E6%93%8A%E5%AE%B6%E6%97%8F%E5%85%AC%E5%8F%B8%E7%8F%BE%E5%A0%B4-%E6%B2%92%E4%BA%BA%E4%B8%8A%E7%8F%AD-061900949.html",
      "headLine": "車銀優爆賺千億卻逃稅 《D社》直擊家族公司現場「沒人上班」",
      "publishDate": "2026-01-24T06:19:00.000Z",
      "source": "{\"@context\":\"http://schema.org\",\"@type\":\"NewsArticle\",\"mainEntityOfPage\":\"https://tw.news.yahoo.com/%E8%BB%8A%E9%8A%80%E5%84%AA%E7%88%86%E8%B3%BA%E5%8D%83%E5%84%84%E5%8D%BB%E9%80%83%E7%A8%85-d%E7%A4%BE-%E7%9B%B4%E6%93%8A%E5%AE%B6%E6%97%8F%E5%85%AC%E5%8F%B8%E7%8F%BE%E5%A0%B4-%E6%B2%92%E4%BA%BA%E4%B8%8A%E7%8F%AD-061900949.html\",\"headline\":\"車銀優爆賺千億卻逃稅 《D社》直擊家族公司現場「沒人上班」\",\"datePublished\":\"2026-01-24T06:19:00.000Z\",\"dateModified\":\"2026-01-24T06:19:00.000Z\",\"keywords\":[\"Chas Gallery\"],\"description\":\"【緯來新聞網】南韓男團ASTRO成員及演員車銀優（Cha Eun-woo）近期遭國稅廳發出稅務補繳通\",\"publisher\":{\"@type\":\"Organization\",\"name\":\"Yahoo奇摩新聞\",\"logo\":{\"@type\":\"ImageObject\",\"url\":\"https://s.yimg.com/cv/apiv2/twmobi/icon/yahoo_tw_logo_structuredata_20200630.png\",\"width\":136,\"height\":60}},\"author\":{\"@type\":\"Person\",\"name\":\"編輯周欣儀／綜合報導\",\"url\":\"\",\"jobTitle\":\"\"},\"creator\":{\"@type\":\"Person\",\"name\":\"編輯周欣儀／綜合報導\",\"url\":\"\",\"jobTitle\":\"\"},\"provider\":{\"@type\":\"Organization\",\"name\":\"緯來新聞網\",\"url\":\"https://news.videoland.com.tw/\",\"logo\":{\"@type\":\"ImageObject\",\"width\":300,\"height\":53,\"url\":\"https://s.yimg.com/os/creatr-uploaded-images/2024-02/40610250-d6b8-11ee-bf8b-59a598dcd994\"}},\"image\":{\"@type\":\"ImageObject\",\"url\":\"https://s.yimg.com/ny/api/res/1.2/SHlzpavOeNdIRLlyYT_.iQ--/YXBwaWQ9aGlnaGxhbmRlcjt3PTE3NjA7aD0xMTA0/https://media.zenfs.com/ko/__647/7ac9ce2ba3cbf1def7be682a955734eb\",\"height\":552,\"width\":880},\"thumbnailUrl\":\"https://s.yimg.com/ny/api/res/1.2/SHlzpavOeNdIRLlyYT_.iQ--/YXBwaWQ9aGlnaGxhbmRlcjt3PTE3NjA7aD0xMTA0/https://media.zenfs.com/ko/__647/7ac9ce2ba3cbf1def7be682a955734eb\"}",
      "content": "【緯來新聞網】南韓男團ASTRO成員及演員車銀優（Cha Eun-woo）近期遭國稅廳發出稅務補繳通知，初步評估其應補繳超過200億韓元稅款。對此，所屬經紀公司Fantagio表示，案件尚處於行政審查階段，是否須繳稅及具體金額皆未定案。《Dispatch》則報導，車銀優成立個人公司後至少賺近1千億，全權交由家人打理公司，不過查訪公司實際地點發現內部殘破不勘，也沒有人上班，事件引發關注。車銀優爆賺千億卻逃稅。（圖／車銀優IG）廣告廣告根據韓國知名娛樂媒體《Dispatch》報導，車銀優於2019年設立的一間名為「Chas Gallery」（차스갤러리）的股份有限公司。該公司成立於安養市，登記代表人為車銀優，董事及監察人分別為其父母。公司營業項目廣泛，涵蓋演藝經紀、公演策劃、廣告、化妝品流通、餐飲業及資產管理等共34項。「Chas Gallery」後續數次遷址，最終設於仁川江華郡불은面，正是車銀優雙親經營鰻魚店的所在地。2020年，車母崔姓女士接任公司代表董事，並於2022年另設有限責任公司「엘앤씨」（L&C），2024年再成立「디애니」（The Any），分別負責實質營運及資產管理，地址亦與鰻魚店相同。《D社》直擊家族公司現場「沒人上班」。（圖／翻攝Dispatch官網）三間公司形成以家族為主體的經營架構，「Chas Gallery」於2024年停止營運成為空殼公司，業務重心轉移至新設立的兩家有限責任公司。儘管車銀優家族公司外觀上為經紀與資產管理機構，國稅廳質疑其利用法人結構迴避個人高額稅負，導致逃漏稅金額可能高達200億韓元。依據法人稅率20推算，차스갤러里至少需申報利潤1,000億韓元以上，實際營業額可能更高。相較之下，個人所得稅的最高邊際稅率達49.5，法人最高實際稅率約為26.4，形成約20的稅負落差，且法人可列報各項營運費用，進一步減輕稅金。外界亦關注車銀優設立個人公司是否與Fantagio過往經營問題有關。2016年，Fantagio陷入資本侵蝕，由中國資本介入接管。2019年，中資母公司JC集團爆發詐欺醜聞，當時Fantagio前景不明，車銀優可能因此設立「Chas Gallery」以保有經濟自主權。車銀優在2022年已與Fantagio續簽合約，據悉簽下偶像圈頂級待遇，仍選擇另設公司收取演藝酬勞。媒體指出，若其母親僅於拍攝現場擔任助理，應由Fantagio支付勞務費即可，無需再由家族公司整體承接其報酬，這成為國稅廳追稅的關鍵疑點。更多緯來新聞網報導陳勢安身體力行送愛受暴家庭 工作空檔扮裝王爺無違和15電豹女同框出席見面會 隊長小楓怕過情人節有慘痛回憶",
      "imageUrl": "https://s.yimg.com/ny/api/res/1.2/uUwxXo44CdfD245GytmEYg--/YXBwaWQ9aGlnaGxhbmRlcjt3PTk2MDtoPTYwMg--/https://media.zenfs.com/ko/__647/7ac9ce2ba3cbf1def7be682a955734eb",
      "imageProvider": null,
      "authorName": "編輯周欣儀／綜合報導",
      "newsProvider": "緯來新聞網",
      "suggestLine": "1. 車銀優補稅200億！\n2. 偶像空殼公司揭密\n3. 賺千億，卻逃稅？\n4. 車銀優陷查稅風暴"
    },
    {
      "link": "https://tw.news.yahoo.com/sj%E9%AB%98%E9%9B%84%E5%B7%A8%E8%9B%8B%E9%96%8B%E5%94%B1%E5%A4%A7%E5%96%8A-%E5%9B%9E%E5%AE%B6%E4%BA%86-%E5%9C%AD%E8%B3%A2%E6%92%82%E5%8F%B0%E8%AA%9E-%E6%AF%8D%E6%B9%AF-%E7%AC%91%E7%BF%BB%E5%85%A8%E5%A0%B4-061120321.html",
      "headLine": "SJ高雄巨蛋開唱大喊「回家了」 圭賢撂台語「母湯」笑翻全場",
      "publishDate": "2026-01-24T06:11:20.000Z",
      "source": "{\"@context\":\"http://schema.org\",\"@type\":\"NewsArticle\",\"mainEntityOfPage\":\"https://tw.news.yahoo.com/sj%E9%AB%98%E9%9B%84%E5%B7%A8%E8%9B%8B%E9%96%8B%E5%94%B1%E5%A4%A7%E5%96%8A-%E5%9B%9E%E5%AE%B6%E4%BA%86-%E5%9C%AD%E8%B3%A2%E6%92%82%E5%8F%B0%E8%AA%9E-%E6%AF%8D%E6%B9%AF-%E7%AC%91%E7%BF%BB%E5%85%A8%E5%A0%B4-061120321.html\",\"headline\":\"SJ高雄巨蛋開唱大喊「回家了」 圭賢撂台語「母湯」笑翻全場\",\"datePublished\":\"2026-01-24T06:11:20.000Z\",\"dateModified\":\"2026-01-24T06:11:20.000Z\",\"keywords\":[\"SUPER JUNIOR\",\"高雄巨蛋\",\"粉絲\",\"SUJU\"],\"description\":\"韓流帝王SUPER JUNIOR相隔2年重返高雄巨蛋，23日晚間舉行三連唱首場，吸引近萬名E.L.F（粉絲名）到場支持，粉絲熱情喊出「歡迎回家」，成員們也在台上深情回應：「我們回家了！」，揭開三連唱的序幕。\",\"publisher\":{\"@type\":\"Organization\",\"name\":\"Yahoo奇摩新聞\",\"logo\":{\"@type\":\"ImageObject\",\"url\":\"https://s.yimg.com/cv/apiv2/twmobi/icon/yahoo_tw_logo_structuredata_20200630.png\",\"width\":136,\"height\":60}},\"author\":{\"@type\":\"Person\",\"name\":\"鄧佩雯\",\"url\":\"\",\"jobTitle\":\"\"},\"creator\":{\"@type\":\"Person\",\"name\":\"鄧佩雯\",\"url\":\"\",\"jobTitle\":\"\"},\"provider\":{\"@type\":\"Organization\",\"name\":\"中天新聞網\",\"url\":\"https://www.ctinews.com/\",\"logo\":{\"@type\":\"ImageObject\",\"width\":1296,\"height\":340,\"url\":\"https://s.yimg.com/os/creatr-uploaded-images/2024-05/70020690-110e-11ef-bffd-6e955363ad96\"}},\"image\":{\"@type\":\"ImageObject\",\"url\":\"https://s.yimg.com/ny/api/res/1.2/FdrpwE_doPoxxpw9TSv4Cw--/YXBwaWQ9aGlnaGxhbmRlcjt3PTI0MDA7aD0xNjAw/https://media.zenfs.com/ko/gotv_ctitv_com_tw_678/6088dd62c8bfd1424a403361d049cd38\",\"height\":800,\"width\":1200},\"thumbnailUrl\":\"https://s.yimg.com/ny/api/res/1.2/FdrpwE_doPoxxpw9TSv4Cw--/YXBwaWQ9aGlnaGxhbmRlcjt3PTI0MDA7aD0xNjAw/https://media.zenfs.com/ko/gotv_ctitv_com_tw_678/6088dd62c8bfd1424a403361d049cd38\"}",
      "content": "韓流帝王SUPER JUNIOR相隔2年重返高雄巨蛋，23日晚間舉行三連唱首場，吸引近萬名E.L.F（粉絲名）到場支持，粉絲熱情喊出「歡迎回家」，成員們也在台上深情回應：「我們回家了！」，揭開三連唱的序幕。演唱會以〈Twins〉、〈U〉、〈It's you〉三首經典歌曲揭開序幕，9位成員使出渾身解數征服全場。神童嘴甜喊出「我愛你們」，厲旭看到粉絲熱情高漲，興奮地問大家：「有信心嗎？」東海則直接拋出飛吻，引爆現場尖叫聲。藝聲感性表示：「看到大家這樣我就沒遺憾了」。廣告廣告SUPER JUNIOR重返高雄巨蛋開唱。（圖／讀者提供）始源因感冒向現場粉絲致歉，自責地說應該要管理好自己的身體，沒想到圭賢竟在旁邊補刀：「對對」，讓現場又是一陣爆笑。圭賢除了秀台語「哇洗圭賢」，還幽默提醒粉絲：「今天是第一天，你們不能累！母湯喔！」相隔多年才來高雄的希澈則大喊「我愛鼎王」，表達對台灣美食的喜愛。銀赫在舞台上唱起他的solo歌曲「自體發光寶石美男 李赫宰 (Say My Name)」，現場粉絲也隨即熱情應援。團長利特則如往常一樣，先拉長音呼喊「高雄～！」，接著驚喜表示：「我以為台北對我們狂熱，原來高雄也這麼狂熱！聽說從上週開始不得了，信號燈過馬路就是SUJU的歌詞、地鐵也是SUJU，全部都是SUJU！我回來了！！！」展現了對高雄城市應援的感動。SUPER JUNIOR在高雄巨蛋一連演唱三天。（圖／讀者提供）台灣粉絲的應援創意一向讓SUPER JUNIOR成員期待，這次也不例外，準備了寫著「到現在只有一點喜歡」與「騙你的，喜歡到停不下來」的應援手幅。利特看到後真心告白：「大家停不下來的喜歡讓SJ可以走到現在，因為大家給我們的愛意我讓我們想要回報，所以送給大家這首歌〈至少還有你〉。」SUPER JUNIOR在完成首場演出後，接下來的週六、週日在高雄巨蛋繼續舉行兩場演唱會，門票已經全數售罄。更多相關訊息可洽iMe TW官方社群專頁查詢。延伸閱讀談台美關係！ 林右昌：美國需要台灣的幫忙每天用卻不知道！「抽取式衛生紙」台灣發明的提台灣「0次」！美最新國防戰略出爐 重申嚇阻陸以實力非對抗",
      "imageUrl": "https://s.yimg.com/ny/api/res/1.2/mucGomjbYMzJekT5f.IH0w--/YXBwaWQ9aGlnaGxhbmRlcjt3PTk2MDtoPTY0MA--/https://media.zenfs.com/ko/gotv_ctitv_com_tw_678/6088dd62c8bfd1424a403361d049cd38",
      "imageProvider": "SUPER JUNIOR重返高雄巨蛋開唱。（圖／讀者提供）",
      "authorName": "鄧佩雯",
      "newsProvider": "中天新聞網",
      "suggestLine": "1. SJ回家了！高雄暴動！\n2. 圭賢神補刀！全場爆笑！\n3. 利特驚呼高雄狂熱！\n4. 粉絲應援！SJ感性告白！"
    },
    {
      "link": "https://tw.news.yahoo.com/%E7%8D%A8%E5%AE%B6-%E6%8F%AD%E5%82%AC%E6%B7%9A-%E6%AD%B9%E6%89%80%E5%9C%A8-%E5%96%9D%E7%B1%B3%E9%BA%A9%E7%95%B6-%E9%A4%90-094300619.html",
      "headLine": "獨家／揭催淚「歹所在」…喝米麩當一餐 艱苦嬤拒善心幫修屋：毋通浪費",
      "publishDate": "2026-01-24T09:43:00.000Z",
      "source": "{\"@context\":\"http://schema.org\",\"@type\":\"NewsArticle\",\"mainEntityOfPage\":\"https://tw.news.yahoo.com/%E7%8D%A8%E5%AE%B6-%E6%8F%AD%E5%82%AC%E6%B7%9A-%E6%AD%B9%E6%89%80%E5%9C%A8-%E5%96%9D%E7%B1%B3%E9%BA%A9%E7%95%B6-%E9%A4%90-094300619.html\",\"headline\":\"獨家／揭催淚「歹所在」…喝米麩當一餐 艱苦嬤拒善心幫修屋：毋通浪費\",\"datePublished\":\"2026-01-24T09:43:00.000Z\",\"dateModified\":\"2026-01-24T09:43:00.000Z\",\"keywords\":[\"張雅筑\",\"陳永聰\",\"楊阿嬤\"],\"description\":\"在酷暑已成常態的現今，空調幾乎是家家戶戶的標配，難以想像若沒了冷氣，日子該如何煎熬。然而，對家住彰化的76歲楊阿嬤而言，這不過是日常。她棲身的土角厝早已殘破不堪，不僅夏日悶熱，連寒冬深夜想上廁所，都得頂著寒風走到屋外。面對簡陋艱苦的環境，阿嬤總帶著苦笑自嘲：「這是歹所在啦（壞地方）」，隨即又坦然地補上一句：「能生...\",\"publisher\":{\"@type\":\"Organization\",\"name\":\"Yahoo奇摩新聞\",\"logo\":{\"@type\":\"ImageObject\",\"url\":\"https://s.yimg.com/cv/apiv2/twmobi/icon/yahoo_tw_logo_structuredata_20200630.png\",\"width\":136,\"height\":60}},\"author\":{\"@type\":\"Person\",\"name\":\"三立新聞網\",\"url\":\"\",\"jobTitle\":\"\"},\"creator\":{\"@type\":\"Person\",\"name\":\"三立新聞網\",\"url\":\"\",\"jobTitle\":\"\"},\"provider\":{\"@type\":\"Organization\",\"name\":\"三立新聞網 setn.com\",\"url\":\"http://www.setn.com/\",\"logo\":{\"@type\":\"ImageObject\",\"width\":316,\"height\":48,\"url\":\"https://s.yimg.com/os/creatr-uploaded-images/2025-01/2c15e170-d866-11ef-97ff-6019437716ae\"}},\"image\":{\"@type\":\"ImageObject\",\"url\":\"https://s.yimg.com/ny/api/res/1.2/FejsJd04uUvnYZNRAyJZlw--/YXBwaWQ9aGlnaGxhbmRlcjt3PTI0MDA7aD0xMzUw/https://media.zenfs.com/zh-tw/setn.com.tw/ff84fc3d071b3c012f2c9933b1d6402e\",\"height\":675,\"width\":1200},\"thumbnailUrl\":\"https://s.yimg.com/ny/api/res/1.2/FejsJd04uUvnYZNRAyJZlw--/YXBwaWQ9aGlnaGxhbmRlcjt3PTI0MDA7aD0xMzUw/https://media.zenfs.com/zh-tw/setn.com.tw/ff84fc3d071b3c012f2c9933b1d6402e\"}",
      "content": "",
      "imageUrl": "https://s.yimg.com/ny/api/res/1.2/96_Q5CyhagC00bSbdHjF8Q--/YXBwaWQ9aGlnaGxhbmRlcjt3PTk2MDtoPTU0MA--/https://media.zenfs.com/zh-tw/setn.com.tw/ff84fc3d071b3c012f2c9933b1d6402e",
      "imageProvider": "76歲的楊阿嬤指著屋內的一道道裂痕，她說，那是921大地震時留下的，那晚搖得很厲害，我抱著、牽著兩個孫女拚命往外跑，很怕家就垮掉。（圖／記者張雅筑攝）",
      "authorName": "三立新聞網",
      "newsProvider": "三立新聞網 setn.com",
      "suggestLine": "很抱歉，您提到「前面要請你閱讀的新聞內容如下：」但實際內容並未提供。\n\n由於我沒有具體的新聞內容可以參考，我將根據一般常見新聞的吸引力要素，為您產出4句通用的引導式句子，希望能符合您的要求：\n\n1.  驚人內幕曝光！\n2.  結局萬萬想不到！\n3.  這件事與你相關！\n4.  重大消息別錯過！"
    },
    {
      "link": "https://tw.news.yahoo.com/%E5%89%8D%E6%9A%97%E9%BB%91%E5%A4%A9%E5%90%8E%E8%92%BC%E4%BA%95%E7%A9%BA%E7%AA%81%E8%A1%A8%E6%85%8B-%E5%97%A8%E5%96%8A-%E6%88%91%E5%96%9C%E6%AD%A1%E4%B8%AD%E5%9C%8B-%E9%81%AD%E7%BD%B5%E7%88%86-055125211.html",
      "headLine": "前暗黑天后蒼井空突表態！嗨喊「我喜歡中國」遭罵爆",
      "publishDate": "2026-01-24T09:42:42.000Z",
      "source": "{\"@context\":\"http://schema.org\",\"@type\":\"NewsArticle\",\"mainEntityOfPage\":\"https://tw.news.yahoo.com/%E5%89%8D%E6%9A%97%E9%BB%91%E5%A4%A9%E5%90%8E%E8%92%BC%E4%BA%95%E7%A9%BA%E7%AA%81%E8%A1%A8%E6%85%8B-%E5%97%A8%E5%96%8A-%E6%88%91%E5%96%9C%E6%AD%A1%E4%B8%AD%E5%9C%8B-%E9%81%AD%E7%BD%B5%E7%88%86-055125211.html\",\"headline\":\"前暗黑天后蒼井空突表態！嗨喊「我喜歡中國」遭罵爆\",\"datePublished\":\"2026-01-24T09:42:42.000Z\",\"dateModified\":\"2026-01-24T09:42:42.000Z\",\"keywords\":[\"蒼井空\"],\"description\":\"娛樂中心／楊佩怡報導有「暗黑界天后」之稱的日本女星蒼井空，2017年正式從暗黑界引退，隔年便宣布結婚喜訊，婚後育有一對雙胞胎兒子。自成人影視界隱退後，她致力於個人品牌的多元化發展，透過社群媒體與創立情趣用品品牌，成功在中國市場開拓廣大版圖並累積深厚人氣。然而近日，樣來不談論政治話題的蒼井空，突然在社群上說出「我喜...\",\"publisher\":{\"@type\":\"Organization\",\"name\":\"Yahoo奇摩新聞\",\"logo\":{\"@type\":\"ImageObject\",\"url\":\"https://s.yimg.com/cv/apiv2/twmobi/icon/yahoo_tw_logo_structuredata_20200630.png\",\"width\":136,\"height\":60}},\"author\":{\"@type\":\"Person\",\"name\":\"民視新聞網\",\"url\":\"\",\"jobTitle\":\"\"},\"creator\":{\"@type\":\"Person\",\"name\":\"民視新聞網\",\"url\":\"\",\"jobTitle\":\"\"},\"provider\":{\"@type\":\"Organization\",\"name\":\"民視\",\"url\":\"https://www.ftvnews.com.tw/\",\"logo\":{\"@type\":\"ImageObject\",\"width\":300,\"height\":50,\"url\":\"https://s.yimg.com/os/creatr-uploaded-images/2020-09/cc0a4a40-fd32-11ea-bdce-e1b4e3c6229a\"}},\"image\":{\"@type\":\"ImageObject\",\"url\":\"https://s.yimg.com/ny/api/res/1.2/l6vrQS0dtiKmLnF7XB3e3Q--/YXBwaWQ9aGlnaGxhbmRlcjt3PTk2MDtoPTQwNA--/https://media.zenfs.com/en/ftvn.com.tw/aec6440b50647255ddabd50efd8620af\",\"height\":271,\"width\":644},\"thumbnailUrl\":\"https://s.yimg.com/ny/api/res/1.2/l6vrQS0dtiKmLnF7XB3e3Q--/YXBwaWQ9aGlnaGxhbmRlcjt3PTk2MDtoPTQwNA--/https://media.zenfs.com/en/ftvn.com.tw/aec6440b50647255ddabd50efd8620af\"}",
      "content": "娛樂中心／楊佩怡報導有「暗黑界天后」之稱的日本女星蒼井空，2017年正式從暗黑界引退，隔年便宣布結婚喜訊，婚後育有一對雙胞胎兒子。自成人影視界隱退後，她致力於個人品牌的多元化發展，透過社群媒體與創立情趣用品品牌，成功在中國市場開拓廣大版圖並累積深厚人氣。然而近日，樣來不談論政治話題的蒼井空，突然在社群上說出「我喜歡中國」5字，瞬間讓日本網友炸鍋。前暗黑天后蒼井空突談政治！嗨喊「我喜歡中國」…日網全炸鍋怒嗆：中國狗蒼井空突在社群平台上高喊「我喜歡中國」。（圖／翻攝自蒼井空X平台）廣告廣告時常在社群平台分享日常生活的蒼井空，近日突然發文大談政治話題。她表示自己在中國有很多好朋友，所以當發生政治動盪時，她都會很難過，因為自己不能去中國看他們，對方也不能來日本。雖然有很多壞消息，但也還是有很多好消息，最後她在文末寫下「私は中国好きよ（我喜歡中國）」。貼文曝光後，大批中國網友在留言區表達對她的支持「蒼老師我喜歡您很久了」、「蒼老師我們都看盜版的你也不介意你好偉大」、「蒼井空老師最棒」。不過這段話也引發日本網友罵聲一遍「你最好不要接受中國共產黨的錢」、「你是在宣傳中國的好嗎？」、「公開談論中國並非保守主義」、「你最好還是保持沉默」、「你說你熱愛中國，但你不知道西藏和維吾爾族正在遭受武力壓迫和控制嗎？」。前暗黑天后蒼井空突談政治！嗨喊「我喜歡中國」…日網全炸鍋怒嗆：中國狗蒼井空不甩爭議，不僅沒道歉，更二次發文喊「我喜歡中國，也喜歡中國人」。（圖／翻攝自蒼井空X平台）面對質疑聲浪，蒼井空並沒有正面道歉，而是再度發文闡述觀點，她坦言在中國生活確實會感到受限，因為「你永遠不知道誰在監視你，也不知道他們在哪裡」。她強調，自己非常慶幸身為日本人，擁有能自由發言的權利，然而她卻話鋒一轉說道：「但我喜歡中國，也喜歡中國人」，她還直言：「所以我只希望當權者們能夠和睦相處」。當回應貼文一出，還是遭到一票日本網友撻伐，而她也只是逐一轉發並回覆。此外，還有網友嗆她是中國狗，蒼井空則態度強硬的反嗆：「大家覺得我是中國狗嗎？好可愛！汪汪」。前暗黑天后蒼井空突談政治！嗨喊「我喜歡中國」…日網全炸鍋怒嗆：中國狗遭網罵是「中國狗」，她正面回應表示「大家覺得我是中國狗嗎？好可愛！汪汪」。（圖／翻攝自蒼井空X平台）原文出處：「前暗黑天后」蒼井空突談政治！嗨喊「我喜歡中國」…日網炸鍋：宣傳中國的好？更多民視新聞報導身體形成一個「X形」！女老師「激戰教學片」無碼外流吳慷仁將中國電影男主？遭中網抵制：風險藝人X形老師賣「無碼實戰片」海撈1憶！前員工再抖大尺度黑料",
      "imageUrl": "https://s.yimg.com/ny/api/res/1.2/l6vrQS0dtiKmLnF7XB3e3Q--/YXBwaWQ9aGlnaGxhbmRlcjt3PTk2MDtoPTQwNA--/https://media.zenfs.com/en/ftvn.com.tw/aec6440b50647255ddabd50efd8620af",
      "imageProvider": "前暗黑天后蒼井空突談政治！嗨喊「我喜歡中國」…日網全炸鍋怒嗆：中國狗",
      "authorName": "民視新聞網",
      "newsProvider": "民視",
      "suggestLine": "1. 蒼井空愛中國，日網全炸鍋！\n2. 天后挺中國，遭日網狂轟。\n3. 「我愛中國」！蒼井空槓上日網。\n4. 蒼井空被罵翻，反嗆「汪汪」。"
    },
    {
      "link": "https://tw.news.yahoo.com/%E8%94%A1%E5%B0%9A%E6%A8%BA%E5%B0%BE%E7%89%99%E6%85%98%E6%91%94-%E9%98%BFken%E7%A7%81%E4%B8%8B-2%E6%9A%96%E8%88%89-%E6%9B%9D%E5%85%89-093348577.html",
      "headLine": "蔡尚樺尾牙慘摔！阿Ken私下「2暖舉」曝光",
      "publishDate": "2026-01-24T09:33:48.000Z",
      "source": "{\"@context\":\"http://schema.org\",\"@type\":\"NewsArticle\",\"mainEntityOfPage\":\"https://tw.news.yahoo.com/%E8%94%A1%E5%B0%9A%E6%A8%BA%E5%B0%BE%E7%89%99%E6%85%98%E6%91%94-%E9%98%BFken%E7%A7%81%E4%B8%8B-2%E6%9A%96%E8%88%89-%E6%9B%9D%E5%85%89-093348577.html\",\"headline\":\"蔡尚樺尾牙慘摔！阿Ken私下「2暖舉」曝光\",\"datePublished\":\"2026-01-24T09:33:48.000Z\",\"dateModified\":\"2026-01-24T09:33:48.000Z\",\"keywords\":[\"蕭煌奇\",\"蔡尚樺\",\"阿Ken\"],\"description\":\"娛樂中心／曾詠晞報導知名主持人蔡尚樺近日接下仁寶尾牙的主持棒，這場活動請來許多重量級卡司，包括告五人、梁靜茹、蕭煌奇、陳華等大咖歌手都到場表演。不過，就在大家看得正開心時，台上卻發生了一個小意外。蔡尚樺在引導蕭煌奇的時候，不小心在階梯上重重摔了一跤，畫面流出後讓許多粉絲擔心，幸好她和搭檔阿Ken、金曲歌王蕭煌奇反...\",\"publisher\":{\"@type\":\"Organization\",\"name\":\"Yahoo奇摩新聞\",\"logo\":{\"@type\":\"ImageObject\",\"url\":\"https://s.yimg.com/cv/apiv2/twmobi/icon/yahoo_tw_logo_structuredata_20200630.png\",\"width\":136,\"height\":60}},\"author\":{\"@type\":\"Person\",\"name\":\"民視新聞網\",\"url\":\"\",\"jobTitle\":\"\"},\"creator\":{\"@type\":\"Person\",\"name\":\"民視新聞網\",\"url\":\"\",\"jobTitle\":\"\"},\"provider\":{\"@type\":\"Organization\",\"name\":\"民視\",\"url\":\"https://www.ftvnews.com.tw/\",\"logo\":{\"@type\":\"ImageObject\",\"width\":300,\"height\":50,\"url\":\"https://s.yimg.com/os/creatr-uploaded-images/2020-09/cc0a4a40-fd32-11ea-bdce-e1b4e3c6229a\"}},\"image\":{\"@type\":\"ImageObject\",\"url\":\"https://s.yimg.com/ny/api/res/1.2/TE8Ay9klBVQwoF5BXeu5SQ--/YXBwaWQ9aGlnaGxhbmRlcjt3PTIwNDg7aD0xMjky/https://media.zenfs.com/en/ftvn.com.tw/df77d95bece12ba54c6bd80e49c78a0d\",\"height\":646,\"width\":1024},\"thumbnailUrl\":\"https://s.yimg.com/ny/api/res/1.2/TE8Ay9klBVQwoF5BXeu5SQ--/YXBwaWQ9aGlnaGxhbmRlcjt3PTIwNDg7aD0xMjky/https://media.zenfs.com/en/ftvn.com.tw/df77d95bece12ba54c6bd80e49c78a0d\"}",
      "content": "娛樂中心／曾詠晞報導知名主持人蔡尚樺近日接下仁寶尾牙的主持棒，這場活動請來許多重量級卡司，包括告五人、梁靜茹、蕭煌奇、陳華等大咖歌手都到場表演。不過，就在大家看得正開心時，台上卻發生了一個小意外。蔡尚樺在引導蕭煌奇的時候，不小心在階梯上重重摔了一跤，畫面流出後讓許多粉絲擔心，幸好她和搭檔阿Ken、金曲歌王蕭煌奇反應超快，開玩笑的化解現場尷尬的氣氛。蔡尚樺仁寶尾牙「驚天一摔」！蕭煌奇、阿Ken「3人對話」化解萬人尷尬蔡尚樺（左圖右）在主持仁寶尾牙時慘跌階梯，幸好平安沒出意外，當下搭檔阿Ken（左圖中）和蕭煌奇（左圖左）用巧妙對話順利救場。（圖／翻攝自IG ＠gladys.tsai）廣告廣告蔡尚樺仁寶尾牙「驚天一摔」！蕭煌奇、阿Ken「3人對話」化解萬人尷尬蔡尚樺事後在IG發文詳細說明這場意外，同時感謝搭檔阿Ken和金曲歌王蕭煌奇的即時救場。（圖／翻攝自IG ＠gladys.tsai）蔡尚樺尾牙意外跌倒！蕭煌奇、阿Ken聯手化解尷尬蔡尚樺事後在IG發文分享這段過程，她開玩笑地說：「我怎麼會在台上發生這麼搞笑的事！」當時蕭煌奇正準備走下台階，去跟搖滾區的觀眾互動，她心想蕭煌奇眼睛看不見，要前去扶他比較安全。沒想到她才剛走過去，就直接在大家面前摔倒，全場觀眾都嚇到安靜了一秒。她自嘲當時真的糗翻天，甚至「差點還要讓蕭煌奇老師扶我起來」，起步後她迅速對著麥克風說「我先摔倒了」，用幽默化解當下的難堪。蔡尚樺仁寶尾牙「驚天一摔」！蕭煌奇、阿Ken「3人對話」化解萬人尷尬知名主持人蔡尚樺最近尾牙主持接滿滿，這場意外的小插曲也讓大眾看見她的主持功底相當深厚。（圖／翻攝自IG ＠gladys.tsai）蔡尚樺仁寶尾牙「驚天一摔」！蕭煌奇、阿Ken「3人對話」化解萬人尷尬阿Ken（左圖）在後台送上自家甜甜圈安慰蔡尚樺（右圖左），還在下班路上貼心幫她提包、遮雨。（圖／翻攝自IG ＠gladys.tsai）蕭煌奇開玩笑要過肩摔、阿Ken私下超暖送甜甜圈這場意外也展現了三人的好感情，剛拿到柔道金牌的蕭煌奇馬上接話，開玩笑說自己有練過柔道，所以沒事；阿Ken則是在旁邊補刀說：「你練過柔道，結果一轉身換她跌倒了。」逗得全場大笑。雖然阿Ken在台上笑得很大聲，但蔡尚樺透露他私底下其實超級貼心，在事發後馬上送來一盒甜甜圈安慰她，工作結束後還幫她提包包、擋雨，並護送她上車，讓蔡尚樺感動地大讚他是「絕世暖男」。原文出處：蔡尚樺主持尾牙「驚天一摔」！蕭煌奇、阿Ken「3人對話」化解萬人尷尬更多民視新聞報導鄧佳華「公主抱胡文英」畫面曝！他嗨喊：變壯了LuLu結婚前夕曬1物！粉喊：你們值得余天昔太帥「女星會靠上來」？余祥銓抖出內幕嘆：差別待遇",
      "imageUrl": "https://s.yimg.com/ny/api/res/1.2/tuZG90d3t7LqbJrAlM0V0w--/YXBwaWQ9aGlnaGxhbmRlcjt3PTk2MDtoPTYwNg--/https://media.zenfs.com/en/ftvn.com.tw/df77d95bece12ba54c6bd80e49c78a0d",
      "imageProvider": "蔡尚樺仁寶尾牙「驚天一摔」！蕭煌奇、阿Ken「3人對話」化解萬人尷尬",
      "authorName": "民視新聞網",
      "newsProvider": "民視",
      "suggestLine": "好的，這是為這則新聞產生的 4 句引導式句子：\n\n1. 蔡尚樺慘跌！幽默神救援\n2. 尾牙摔跤，秒變脫口秀！\n3. 她跌倒，蕭煌奇差點扶？\n4. 驚天一摔！尷尬瞬間全消"
    },
    {
      "link": "https://tw.news.yahoo.com/%E9%9C%8D%E8%AB%BE%E5%BE%B7%E6%94%80%E5%8F%B0%E5%8C%97101%E5%9B%A0%E9%9B%A8%E5%BB%B6%E6%9C%9F-%E7%B6%B2%E6%B9%A7netflix%E8%87%89%E6%9B%B8%E5%96%8A%E8%A9%B1-%E5%AE%89%E5%85%A8%E7%AC%AC-092619736.html",
      "headLine": "霍諾德攀台北101因雨延期 網湧Netflix臉書喊話「安全第一」",
      "publishDate": "2026-01-24T09:26:19.000Z",
      "source": "{\"@context\":\"http://schema.org\",\"@type\":\"NewsArticle\",\"mainEntityOfPage\":\"https://tw.news.yahoo.com/%E9%9C%8D%E8%AB%BE%E5%BE%B7%E6%94%80%E5%8F%B0%E5%8C%97101%E5%9B%A0%E9%9B%A8%E5%BB%B6%E6%9C%9F-%E7%B6%B2%E6%B9%A7netflix%E8%87%89%E6%9B%B8%E5%96%8A%E8%A9%B1-%E5%AE%89%E5%85%A8%E7%AC%AC-092619736.html\",\"headline\":\"霍諾德攀台北101因雨延期 網湧Netflix臉書喊話「安全第一」\",\"datePublished\":\"2026-01-24T09:26:19.000Z\",\"dateModified\":\"2026-01-24T09:26:19.000Z\",\"keywords\":[\"霍諾德\",\"台北101\",\"Netflix\",\"攀登\",\"安全第一\"],\"description\":\"世界頂尖攀岩家霍諾德（Alex Honnold）原定24日挑戰徒手攀登台北101，不過由於上午飄雨、氣候不佳，Netflix在臉書宣布將延期至25日上午9點進行《赤手獨攀台北101：直播》Skyscraper Live 活動，強調「安全始終是我們的首要考量」感謝大家的理解與體諒。消息曝光後，許多人也紛紛留言喊話「...\",\"publisher\":{\"@type\":\"Organization\",\"name\":\"Yahoo奇摩新聞\",\"logo\":{\"@type\":\"ImageObject\",\"url\":\"https://s.yimg.com/cv/apiv2/twmobi/icon/yahoo_tw_logo_structuredata_20200630.png\",\"width\":136,\"height\":60}},\"author\":{\"@type\":\"Person\",\"name\":\"郭竹倩\",\"url\":\"\",\"jobTitle\":\"\"},\"creator\":{\"@type\":\"Person\",\"name\":\"郭竹倩\",\"url\":\"\",\"jobTitle\":\"\"},\"provider\":{\"@type\":\"Organization\",\"name\":\"中天新聞網\",\"url\":\"https://www.ctinews.com/\",\"logo\":{\"@type\":\"ImageObject\",\"width\":1296,\"height\":340,\"url\":\"https://s.yimg.com/os/creatr-uploaded-images/2024-05/70020690-110e-11ef-bffd-6e955363ad96\"}},\"image\":{\"@type\":\"ImageObject\",\"url\":\"https://s.yimg.com/ny/api/res/1.2/gH2y2FGIZYG3e.t.FBqmPA--/YXBwaWQ9aGlnaGxhbmRlcjt3PTI0MDA7aD0xNjAw/https://media.zenfs.com/en/gotv_ctitv_com_tw_678/160739c5ceb99ac8828bfe62f7577f7e\",\"height\":800,\"width\":1200},\"thumbnailUrl\":\"https://s.yimg.com/ny/api/res/1.2/gH2y2FGIZYG3e.t.FBqmPA--/YXBwaWQ9aGlnaGxhbmRlcjt3PTI0MDA7aD0xNjAw/https://media.zenfs.com/en/gotv_ctitv_com_tw_678/160739c5ceb99ac8828bfe62f7577f7e\"}",
      "content": "世界頂尖攀岩家霍諾德（Alex Honnold）原定24日挑戰徒手攀登台北101，不過由於上午飄雨、氣候不佳，Netflix在臉書宣布將延期至25日上午9點進行《赤手獨攀台北101：直播》Skyscraper Live 活動，強調「安全始終是我們的首要考量」感謝大家的理解與體諒。消息曝光後，許多人也紛紛留言喊話「安全第一」。霍諾德將在25日上午9點挑戰徒手攀登台北101。（圖／翻攝自Netflix臉書）Netflix 24日發文。（圖／翻攝自Netflix臉書）Netflix宣布霍諾德改期至25日挑戰攀登台北101後，網友紛紛留言：「安全第一！期待放晴的好天氣」，「安全第一！希望明天好天氣」、「安全第一，加油」、「安全第一！挑戰不是玩命， 專業至上，支持」、「沒關係，安全第一」、「安全第一，等著看Alex爬到避雷針」、「安全絕對是第一」、「安全第一，延多久都沒關係」、「支持延期，如果明天一樣下雨請繼續延期，為了安全請採取最高標準」。廣告廣告霍諾德24日表示很遺憾因下雨無法攀登台北101。（圖／翻攝自霍諾德臉書）霍諾德25日將挑戰攀登台北101。（圖／翻攝自Netflix臉書）霍諾德也發布自拍影片表示很遺憾今天因下雨無法攀登台北101，改為安排健行行程。也提到攀登必須評估天氣狀況，稱讚台北市是美麗的城市，感謝大家對他的支持與鼓勵。延伸閱讀台積電4成產能移美國 張善政：工程師出走影響超乎想像台積電美國子公司董事改選完成 Sajiv Dalal升任總經理暨執行長台股新二哥來了！台達電漲停創歷史新天價 市值衝3.23兆",
      "imageUrl": "https://s.yimg.com/ny/api/res/1.2/wK1lSxXP13.Do.PgEITVuw--/YXBwaWQ9aGlnaGxhbmRlcjt3PTk2MDtoPTY0MA--/https://media.zenfs.com/en/gotv_ctitv_com_tw_678/160739c5ceb99ac8828bfe62f7577f7e",
      "imageProvider": "霍諾德將在25日上午9點挑戰徒手攀登台北101。（圖／翻攝自Netflix臉書）",
      "authorName": "郭竹倩",
      "newsProvider": "中天新聞網",
      "suggestLine": "好的，這是一則關於世界頂尖攀岩家霍諾德徒手攀登台北101因天氣延期的報導。\n以下為您產出的四句引導式句子：\n\n1. 霍諾德101生變！為何？\n2. 安全優先！101攀登改期。\n3. 101攀登突生變！直播延。\n4. 霍諾德攻101！明早再戰。"
    },
    {
      "link": "https://tw.news.yahoo.com/%E5%86%B0%E7%90%83%E6%A8%82%E5%9C%98%E6%88%90%E8%BB%8D13%E5%B9%B4%E5%88%9D%E9%AB%94%E9%A9%97-%E9%81%93%E6%AD%89-%E9%80%99%E9%BA%BC%E5%BF%AB%E5%B0%B1%E6%B2%92%E4%BA%86-092029899.html",
      "headLine": "冰球樂團成軍13年初體驗 道歉：這麼快就沒了",
      "publishDate": "2026-01-24T09:20:29.000Z",
      "source": "{\"@context\":\"http://schema.org\",\"@type\":\"NewsArticle\",\"mainEntityOfPage\":\"https://tw.news.yahoo.com/%E5%86%B0%E7%90%83%E6%A8%82%E5%9C%98%E6%88%90%E8%BB%8D13%E5%B9%B4%E5%88%9D%E9%AB%94%E9%A9%97-%E9%81%93%E6%AD%89-%E9%80%99%E9%BA%BC%E5%BF%AB%E5%B0%B1%E6%B2%92%E4%BA%86-092029899.html\",\"headline\":\"冰球樂團成軍13年初體驗 道歉：這麼快就沒了\",\"datePublished\":\"2026-01-24T09:20:29.000Z\",\"dateModified\":\"2026-01-24T09:20:29.000Z\",\"keywords\":[\"icyball冰球樂團\",\"台北流行音樂中心\"],\"description\":\"icyball冰球樂團成軍13年，5月2日將在台北流行音樂中心舉辦「我很抱歉」演唱會的門票開賣1分鐘就秒殺，鍵盤手蒙幽默說：「沒想到，第1次，這麼大，這麼快就沒了，我很抱歉。」今（1╱24）也宣布5月3日加唱1場。\",\"publisher\":{\"@type\":\"Organization\",\"name\":\"Yahoo奇摩新聞\",\"logo\":{\"@type\":\"ImageObject\",\"url\":\"https://s.yimg.com/cv/apiv2/twmobi/icon/yahoo_tw_logo_structuredata_20200630.png\",\"width\":136,\"height\":60}},\"author\":{\"@type\":\"Person\",\"name\":\"黃于珊\",\"url\":\"\",\"jobTitle\":\"\"},\"creator\":{\"@type\":\"Person\",\"name\":\"黃于珊\",\"url\":\"\",\"jobTitle\":\"\"},\"provider\":{\"@type\":\"Organization\",\"name\":\"太報\",\"url\":\"https://www.taisounds.com/\",\"logo\":{\"@type\":\"ImageObject\",\"width\":342,\"height\":148,\"url\":\"https://s.yimg.com/os/creatr-uploaded-images/2020-10/313c79c0-0868-11eb-97bf-cd65779af105\"}},\"image\":{\"@type\":\"ImageObject\",\"url\":\"https://s.yimg.com/ny/api/res/1.2/AiInCzKwqiF7VAjGncYu4g--/YXBwaWQ9aGlnaGxhbmRlcjt3PTI0MDA7aD0xMzUy/https://media.zenfs.com/zh-tw/taisounds_com_380/44ee378780f5a915ca554cf7f36d0d3d\",\"height\":676,\"width\":1200},\"thumbnailUrl\":\"https://s.yimg.com/ny/api/res/1.2/AiInCzKwqiF7VAjGncYu4g--/YXBwaWQ9aGlnaGxhbmRlcjt3PTI0MDA7aD0xMzUy/https://media.zenfs.com/zh-tw/taisounds_com_380/44ee378780f5a915ca554cf7f36d0d3d\"}",
      "content": "冰球樂團宣布5月3日加唱1場。何樂音樂提供 icyball冰球樂團成軍13年，5月2日將在台北流行音樂中心舉辦「我很抱歉」演唱會的門票開賣1分鐘就秒殺，鍵盤手蒙幽默說：「沒想到，第1次，這麼大，這麼快就沒了，我很抱歉。」今（1╱24）也宣布5月3日加唱1場。由主唱王與鍵盤手蒙、貝斯手Nelson、鼓手士捷組成的冰球樂團首度站上北流就賣光光，Nelson引用新專輯名稱：「沒搶到票的小可愛，我們先深深一鞠躬——我很抱歉。這張專輯都在道歉，歹謝啦！這次真的不是故意的！」士捷則恭賀：「有搶到票的小可愛，恭喜你，Privilege特權量表加10分！沒有的也不著急，早已習慣把你們寵壞，寵壞的意義是什麼？加場！」王勉勵大家再接再厲，「沒搶到票的小可愛們，我很抱歉，但太容易到手的緣分就沒那麼珍貴了，對吧？別氣餒，加場我們再試1次」。廣告廣告團員們熱情喊話為加場催票，蒙好奇問粉絲：「如果還有第2次，也能這麼快嗎？」Nelson引用新歌呼籲：「聽說很多人上次搶票的時候，明明有點喜歡，但又裝作不在乎，這次加場你還來得及。」士捷邀請大家二刷：「有些歌1晚唱不完，有些人1晚見不夠，下次見面就是下次了。這次，能不能和我留在北流，陪我2天？」王打趣說：「世界好危險，動心又怕受傷害，哪裡才能放膽愛？當然是來冰球的演唱會，1晚上的愛，安全又無害，現在還加開了第2場，還不買爆？」更多太報報導  黃河迎最棘手狀況「超崩潰」 王品澔幫陳姸霏肉搜渣男  曾莞婷、楊銘威爆衝突 風田當苦力怨沒人看到  Lulu陳漢典明大婚先收大禮 郁方親送：還好她不姓藍",
      "imageUrl": "https://s.yimg.com/ny/api/res/1.2/guaSQr9zFmrOkctt66mtfA--/YXBwaWQ9aGlnaGxhbmRlcjt3PTk2MDtoPTU0MQ--/https://media.zenfs.com/zh-tw/taisounds_com_380/44ee378780f5a915ca554cf7f36d0d3d",
      "imageProvider": "冰球樂團宣布5月3日加唱1場。何樂音樂提供",
      "authorName": "黃于珊",
      "newsProvider": "太報",
      "suggestLine": "以下是為您產出的 4 句引導式句子：\n\n1. 冰球秒殺！驚喜加場！\n2. 錯過秒殺？冰球再開！\n3. 冰球道歉：再加場！\n4. 北流爆滿！手刀搶票！"
    },
    {
      "link": "https://tw.news.yahoo.com/%E8%A8%B1%E5%AF%8C%E5%87%B1%E5%B0%BE%E7%89%99%E7%8B%82%E6%8E%A5%E8%B6%85%E9%81%8E20%E5%A0%B4-%E6%9B%9D%E7%88%B6%E8%A6%AA%E9%81%BA%E7%89%A9%E8%97%8F%E8%A1%A3%E6%AB%A5%E8%A7%A3%E6%80%9D%E5%BF%B5%E4%B9%8B%E6%83%85-091900425.html",
      "headLine": "許富凱尾牙狂接超過20場！曝父親遺物藏衣櫥解思念之情",
      "publishDate": "2026-01-24T09:19:00.000Z",
      "source": "{\"@context\":\"http://schema.org\",\"@type\":\"NewsArticle\",\"mainEntityOfPage\":\"https://tw.news.yahoo.com/%E8%A8%B1%E5%AF%8C%E5%87%B1%E5%B0%BE%E7%89%99%E7%8B%82%E6%8E%A5%E8%B6%85%E9%81%8E20%E5%A0%B4-%E6%9B%9D%E7%88%B6%E8%A6%AA%E9%81%BA%E7%89%A9%E8%97%8F%E8%A1%A3%E6%AB%A5%E8%A7%A3%E6%80%9D%E5%BF%B5%E4%B9%8B%E6%83%85-091900425.html\",\"headline\":\"許富凱尾牙狂接超過20場！曝父親遺物藏衣櫥解思念之情\",\"datePublished\":\"2026-01-24T09:19:00.000Z\",\"dateModified\":\"2026-01-24T09:19:00.000Z\",\"keywords\":[\"許富凱\",\"緯來\",\"陳明中\"],\"description\":\"【緯來新聞網】「金曲歌王」許富凱今（24日）擔任緯來電視網主辦「-1111循寶夠物節」壓軸表演嘉賓，\",\"publisher\":{\"@type\":\"Organization\",\"name\":\"Yahoo奇摩新聞\",\"logo\":{\"@type\":\"ImageObject\",\"url\":\"https://s.yimg.com/cv/apiv2/twmobi/icon/yahoo_tw_logo_structuredata_20200630.png\",\"width\":136,\"height\":60}},\"author\":{\"@type\":\"Person\",\"name\":\"記者蔡依庭／台北報導\",\"url\":\"\",\"jobTitle\":\"\"},\"creator\":{\"@type\":\"Person\",\"name\":\"記者蔡依庭／台北報導\",\"url\":\"\",\"jobTitle\":\"\"},\"provider\":{\"@type\":\"Organization\",\"name\":\"緯來新聞網\",\"url\":\"https://news.videoland.com.tw/\",\"logo\":{\"@type\":\"ImageObject\",\"width\":300,\"height\":53,\"url\":\"https://s.yimg.com/os/creatr-uploaded-images/2024-02/40610250-d6b8-11ee-bf8b-59a598dcd994\"}},\"image\":{\"@type\":\"ImageObject\",\"url\":\"https://s.yimg.com/ny/api/res/1.2/JKvvB6hDI0NfR4DQuyr48g--/YXBwaWQ9aGlnaGxhbmRlcjt3PTI0MDA7aD0xODYy/https://media.zenfs.com/ko/__647/adbdb2fea016bd9202e221b0c4d76e37\",\"height\":931,\"width\":1200},\"thumbnailUrl\":\"https://s.yimg.com/ny/api/res/1.2/JKvvB6hDI0NfR4DQuyr48g--/YXBwaWQ9aGlnaGxhbmRlcjt3PTI0MDA7aD0xODYy/https://media.zenfs.com/ko/__647/adbdb2fea016bd9202e221b0c4d76e37\"}",
      "content": "【緯來新聞網】「金曲歌王」許富凱今（24日）擔任緯來電視網主辦「-1111循寶夠物節」壓軸表演嘉賓，同時捐贈人生首場台北小巨蛋演唱會的表演服作為競標物，接受《緯來新聞網》訪問時透露尾牙接了20幾場，會工作到農曆年前，由於去年已帶媽媽去看過江蕙演唱會，所以這回加場就不會去，笑稱將機會留給尚未看過的粉絲。許富凱歌聲動人。（圖／記者陳明中攝）許富凱粉絲黏著度極高，先前曾參與緯來原創節目《夜市王》最終戰的表演嘉賓，吸引大批歌迷聚集，這回現身「-1111循寶夠物節」，看見許多《夜市王》的攤販感到熟悉。提到二手物的購買，他比較常買二手衣物，透露曾在日本古著店看中一件米老鼠復古牛仔外套，認為實在難得就直接買下。提到人生重要的物件，他提到媽媽很愛逛菜市場，常常買二手物品，曾買了一件愛迪達外套給爸爸，現在父親離世了，「我現在都放在衣櫥當最思念的物品，打開都會感到很溫暖」。此外最珍貴的貼身之物就是粉絲集資送的麥克風，「很有安全感，又是粉絲出資送的，更有意義」。廣告廣告許富凱響應公益活動。（圖／記者陳明中攝）「-1111循寶夠物節」以實際行動回應環境與社會議題，以「愛護地球、推動循環經濟」為核心理念，透過舉辦大型公益二手市集，讓每一件物品都能被再次珍惜。今年由緯來電視網主辦，光寶科技、光寶文教基金會協辦，並攜手合作企業皮耶洛實業、兆豐慈善基金會、星展銀行（台灣）、理律法律事務所、凱基銀行、摩根士丹利，共同展現企業投入永續發展與社會關懷的行動力。光寶科技總經理邱森彬、緯來董事長李鐘培、許富凱、光寶文教基金會執行長張衣宜共襄盛舉公益活動。（圖／記者陳明中攝）本次公益所得捐贈單位包含：中華民國徐生明棒球發展協會、天主教白永恩神父社會福利基金會、多寶藝術學堂、伊甸社會福利基金會、台灣兒童暨家庭扶助基金會附設新北市私立大同育幼院、台灣數位有聲書推展學會、孩子的書屋文教基金會、逆風劇團、高雄市私立小天使家園、屏東縣腦性麻痺服務協會及華山社會福利慈善事業基金會。更多緯來新聞網報導陳勢安身體力行送愛受暴家庭 工作空檔扮裝王爺無違和15電豹女同框出席見面會 隊長小楓怕過情人節有慘痛回憶",
      "imageUrl": "https://s.yimg.com/ny/api/res/1.2/G6eJ8EVE2ln19YQRhMVpFA--/YXBwaWQ9aGlnaGxhbmRlcjt3PTk2MDtoPTc0NQ--/https://media.zenfs.com/ko/__647/adbdb2fea016bd9202e221b0c4d76e37",
      "imageProvider": null,
      "authorName": "記者蔡依庭／台北報導",
      "newsProvider": "緯來新聞網",
      "suggestLine": "1. 許富凱思父：舊衣最暖！\n2. 歌王珍藏：麥克風意義深！\n3. 許富凱愛物：不只名牌！\n4. 點開看：歌王寶物揭秘！"
    },
    {
      "link": "https://tw.news.yahoo.com/%E5%B0%8Fs%E6%BA%96%E5%82%99%E5%9B%9E%E6%AD%B8-%E8%A3%BD%E4%BD%9C%E4%BA%BA-%E7%B5%A6%E7%AD%94%E6%A1%88-%E5%8A%A0%E7%A2%BC%E7%88%86%E5%BA%B7%E7%86%99%E5%85%A7%E5%B9%95-091803833.html",
      "headLine": "小S準備回歸？製作人「給答案」加碼爆康熙內幕",
      "publishDate": "2026-01-24T09:18:03.000Z",
      "source": "{\"@context\":\"http://schema.org\",\"@type\":\"NewsArticle\",\"mainEntityOfPage\":\"https://tw.news.yahoo.com/%E5%B0%8Fs%E6%BA%96%E5%82%99%E5%9B%9E%E6%AD%B8-%E8%A3%BD%E4%BD%9C%E4%BA%BA-%E7%B5%A6%E7%AD%94%E6%A1%88-%E5%8A%A0%E7%A2%BC%E7%88%86%E5%BA%B7%E7%86%99%E5%85%A7%E5%B9%95-091803833.html\",\"headline\":\"小S準備回歸？製作人「給答案」加碼爆康熙內幕\",\"datePublished\":\"2026-01-24T09:18:03.000Z\",\"dateModified\":\"2026-01-24T09:18:03.000Z\",\"keywords\":[\"小S\",\"康熙來了\",\"製作人\"],\"description\":\"娛樂中心／杜子心報導大S（徐熙媛）逝世將滿1年，女星小S（徐熙娣）在姊姊病逝後，深陷喪姊之痛，演藝事業停擺至今。對於外界關注她何時回歸螢光幕，小S至今尚未有明確規劃。昔日《康熙來了》製作人B2今（24）日出席緯來電視網公益二手市集「-1111循寶夠物節」，被問及小S復出，他依舊低調回應「她準備好了就會call我」...\",\"publisher\":{\"@type\":\"Organization\",\"name\":\"Yahoo奇摩新聞\",\"logo\":{\"@type\":\"ImageObject\",\"url\":\"https://s.yimg.com/cv/apiv2/twmobi/icon/yahoo_tw_logo_structuredata_20200630.png\",\"width\":136,\"height\":60}},\"author\":{\"@type\":\"Person\",\"name\":\"民視新聞網\",\"url\":\"\",\"jobTitle\":\"\"},\"creator\":{\"@type\":\"Person\",\"name\":\"民視新聞網\",\"url\":\"\",\"jobTitle\":\"\"},\"provider\":{\"@type\":\"Organization\",\"name\":\"民視\",\"url\":\"https://www.ftvnews.com.tw/\",\"logo\":{\"@type\":\"ImageObject\",\"width\":300,\"height\":50,\"url\":\"https://s.yimg.com/os/creatr-uploaded-images/2020-09/cc0a4a40-fd32-11ea-bdce-e1b4e3c6229a\"}},\"image\":{\"@type\":\"ImageObject\",\"url\":\"https://s.yimg.com/ny/api/res/1.2/_ZTpGNxltPxYWKB1J6iaLQ--/YXBwaWQ9aGlnaGxhbmRlcjt3PTE2NDY7aD0xNTY0/https://media.zenfs.com/ko/ftvn.com.tw/e952d8f429612c942a6dd94b185f4e44\",\"height\":782,\"width\":823},\"thumbnailUrl\":\"https://s.yimg.com/ny/api/res/1.2/_ZTpGNxltPxYWKB1J6iaLQ--/YXBwaWQ9aGlnaGxhbmRlcjt3PTE2NDY7aD0xNTY0/https://media.zenfs.com/ko/ftvn.com.tw/e952d8f429612c942a6dd94b185f4e44\"}",
      "content": "娛樂中心／杜子心報導大S（徐熙媛）逝世將滿1年，女星小S（徐熙娣）在姊姊病逝後，深陷喪姊之痛，演藝事業停擺至今。對於外界關注她何時回歸螢光幕，小S至今尚未有明確規劃。昔日《康熙來了》製作人B2今（24）日出席緯來電視網公益二手市集「-1111循寶夠物節」，被問及小S復出，他依舊低調回應「她準備好了就會call我」，他強調私下兩人偶爾閒聊，但不會主動談工作，他尊重小S的節奏與決定。小S復出時間點有譜了？製作人B2低調回應加碼爆《康熙》當年停播原因小S（左）與蔡康永（右）曾一同主持《康熙來了》。（圖／翻攝自IG@kangyongcai）廣告廣告B2不只是昔日《康熙來了》的製作人，同時他也是小S主持的《小姐不熙娣》製作人，他被問及小S回歸《小姐不熙娣》時回應，「我只跟她說，準備好CALL我就好，我不會主動跟她閒聊，但她會跟我閒聊，畢竟我們認識二十幾年了，像是朋友的閒聊，比如她突然想看演唱會等等，我從來沒跟她詢問工作上的事」。同時B2也分享了《康熙來了》停播10週年的回憶，他透露當初節目每天要錄5集，長期緊湊的錄影節奏讓團隊都需要喘口氣。小S復出時間點有譜了？製作人B2低調回應加碼爆《康熙》當年停播原因B2（左）透露自己去年赴東南亞外景時右膝前十字韌帶斷裂。（圖／三立電視畫面提供）有一次B2與蔡康永在後台討論是否該休息，小S當時從廁所走出來，也乾脆地認為「再錄一段時間就結束」，隔天3人便達成共識收攤。B2認為，停在最好的狀態才是對觀眾最好的安排，也說重啟與否對他們現在而言已不是最重要的事。今年雖是停播10週年，B2透露團隊個性隨興，可能只會在社群發文紀念，並沒有大計劃。此外，B2也談到近期工作狀況，透露自己去年赴東南亞外景時右膝前十字韌帶斷裂，硬撐了3個月才動手術，目前仍需復健3到6個月，但仍為3月即將首播的《宇宙啦啦隊》投入心力。原文出處：小S復出時間點有譜了？製作人B2低調回應加碼爆《康熙》當年停播原因更多民視新聞報導斑馬線突然多了「3條神秘直線」！交通部揭暖心用途改吃素反而水腫又變胖？營養師揭素食7地雷日本免稅結帳太慢？台人護照貼1物獲店員大讚",
      "imageUrl": "https://s.yimg.com/ny/api/res/1.2/ni4yKp5Den59ViFIdmb2EA--/YXBwaWQ9aGlnaGxhbmRlcjt3PTk2MDtoPTkxMg--/https://media.zenfs.com/ko/ftvn.com.tw/e952d8f429612c942a6dd94b185f4e44",
      "imageProvider": "小S復出時間點有譜了？製作人B2低調回應加碼爆《康熙》當年停播原因",
      "authorName": "民視新聞網",
      "newsProvider": "民視",
      "suggestLine": "1. 小S復出，答案揭曉？\n2. 康熙停播真相，她一句話！\n3. 小S回歸有譜？製作人說！\n4. 康熙停播內幕，首度曝光！"
    },
    {
      "link": "https://tw.news.yahoo.com/%E5%AE%87%E5%AE%99%E5%95%A6%E5%95%A6%E9%9A%8A-%E9%9B%A8%E4%B8%AD%E7%86%B1%E8%A1%80%E6%87%89%E6%8F%B4-%E5%B0%8B%E5%AF%B6%E5%A4%A0%E7%89%A9%E7%AF%80-%E5%85%AC%E7%9B%8A%E8%88%9E%E5%8F%B0-091500185.html",
      "headLine": "《宇宙啦啦隊》雨中熱血應援「尋寶夠物節」公益舞台",
      "publishDate": "2026-01-24T09:15:00.000Z",
      "source": "{\"@context\":\"http://schema.org\",\"@type\":\"NewsArticle\",\"mainEntityOfPage\":\"https://tw.news.yahoo.com/%E5%AE%87%E5%AE%99%E5%95%A6%E5%95%A6%E9%9A%8A-%E9%9B%A8%E4%B8%AD%E7%86%B1%E8%A1%80%E6%87%89%E6%8F%B4-%E5%B0%8B%E5%AF%B6%E5%A4%A0%E7%89%A9%E7%AF%80-%E5%85%AC%E7%9B%8A%E8%88%9E%E5%8F%B0-091500185.html\",\"headline\":\"《宇宙啦啦隊》雨中熱血應援「尋寶夠物節」公益舞台\",\"datePublished\":\"2026-01-24T09:15:00.000Z\",\"dateModified\":\"2026-01-24T09:15:00.000Z\",\"keywords\":[\"公益義賣活動\",\"啦啦隊\"],\"description\":\"緯來原創選秀節目《宇宙啦啦隊》今（24）日受邀參與「尋寶夠物節」公益義賣活動，25位參賽女孩在寒冷又下雨的天氣中登台演出，即使舞台空間有限，仍以滿滿熱情完成演出，成功替現場注入熱血能量，吸引不少民眾駐足欣賞，也讓公益活動多了青春與笑聲。 活動當天氣溫偏低又飄雨，對穿著啦啦隊短裙、跳高強度舞蹈的女孩們來說是不小挑戰...\",\"publisher\":{\"@type\":\"Organization\",\"name\":\"Yahoo奇摩新聞\",\"logo\":{\"@type\":\"ImageObject\",\"url\":\"https://s.yimg.com/cv/apiv2/twmobi/icon/yahoo_tw_logo_structuredata_20200630.png\",\"width\":136,\"height\":60}},\"author\":{\"@type\":\"Person\",\"name\":\"青年日報\",\"url\":\"\",\"jobTitle\":\"\"},\"creator\":{\"@type\":\"Person\",\"name\":\"青年日報\",\"url\":\"\",\"jobTitle\":\"\"},\"provider\":{\"@type\":\"Organization\",\"name\":\"青年日報\",\"url\":\"https://www.ydn.com.tw/\",\"logo\":{\"@type\":\"ImageObject\",\"width\":336,\"height\":90,\"url\":\"https://s.yimg.com/os/creatr-uploaded-images/2025-12/5dcecbf0-d419-11f0-bfef-ed0eef1617dc\"}},\"image\":{\"@type\":\"ImageObject\",\"url\":\"https://s.yimg.com/ny/api/res/1.2/N_Ae.u00664oQAPDVK_7LQ--/YXBwaWQ9aGlnaGxhbmRlcjt3PTI0MDA7aD0xNTk4/https://media.zenfs.com/ko/youthdailynews_517/54e93f722ac9a07cd0b58900a6d26945\",\"height\":799,\"width\":1200},\"thumbnailUrl\":\"https://s.yimg.com/ny/api/res/1.2/N_Ae.u00664oQAPDVK_7LQ--/YXBwaWQ9aGlnaGxhbmRlcjt3PTI0MDA7aD0xNTk4/https://media.zenfs.com/ko/youthdailynews_517/54e93f722ac9a07cd0b58900a6d26945\"}",
      "content": "記者周毓洵／臺北報導緯來原創選秀節目《宇宙啦啦隊》今（24）日受邀參與「尋寶夠物節」公益義賣活動，25位參賽女孩在寒冷又下雨的天氣中登台演出，即使舞台空間有限，仍以滿滿熱情完成演出，成功替現場注入熱血能量，吸引不少民眾駐足欣賞，也讓公益活動多了青春與笑聲。活動當天氣溫偏低又飄雨，對穿著啦啦隊短裙、跳高強度舞蹈的女孩們來說是不小挑戰。製作人B2（陳彥銘）在會後受訪時坦言相當感動，「天氣真的很冷，又下雨，場地也有限制，但她們表現得非常好，現場觀眾的熱情也感染到我們，大家都跳得很開心。」他直言，這樣的現場回饋，正是節目最想呈現的精神。廣告廣告《宇宙啦啦隊》成員艾莉兒分享，演出時不只要穿短裙，舞風還偏向帥氣路線，加上鞋跟偏高、舞台後方又有階梯，一度差點踩空跌倒，「真的嚇死，還好有穩住！」她笑說，站在台上時腦中只有一個念頭：「不能出事、要撐住氣場。」聊到與《宇宙啦啦隊》主持人SUPER JUNIOR成員銀赫合作一事，女孩們則瞬間笑成一片，異口同聲形容他「很香」。成員紀欣伶透露，第一次近距離接觸銀赫時，就聞到一股熟悉的香味，「那是我平常很喜歡的香水品牌，忍不住直接問他是不是那一款，結果真的猜中！」也讓現場笑聲不斷。女孩們也分享，銀赫私下相當貼心，看到有人因選秀壓力落淚，還會用中文輕聲安慰「不要哭」，讓大家瞬間被融化。談到選秀壓力，女孩們坦言競爭激烈，加上團隊賽制，難免擔心影響彼此表現。《宇宙啦啦隊》歷經半年以上的密集訓練，包含臺灣與韓國雙地培訓，B2 也強調，雖然節目最終會選出9人組成偶像女團，但28位女孩全都是「宇宙啦啦隊」的一份子，未來都將持續參與應援、演出與各類活動，「每個人都會有舞台。」《宇宙啦啦隊》預計於三月正式播出，B2坦言壓力不小，也笑說整個團隊「都滿瘋狂的」，甚至在節目尚未播出前，就已規劃舉辦大型粉絲見面會，場地規模上看500至1000人。他表示，希望在節目開播前，就先讓大家感受到《宇宙啦啦隊》的熱血能量，也讓更多人看見女孩們為夢想努力的模樣。《宇宙啦啦隊》25位參賽女孩冒雨登台演出，在寒冷天氣中仍以滿滿熱情點燃「尋寶夠物節」公益舞台。（緯來電視網提供）",
      "imageUrl": "https://s.yimg.com/ny/api/res/1.2/mcw3fcMA2Cr5phqlkVN53A--/YXBwaWQ9aGlnaGxhbmRlcjt3PTk2MDtoPTY0MA--/https://media.zenfs.com/ko/youthdailynews_517/54e93f722ac9a07cd0b58900a6d26945",
      "imageProvider": null,
      "authorName": "青年日報",
      "newsProvider": "青年日報",
      "suggestLine": "1. 啦啦隊冒雨熱舞\n2. 女孩狂讚：銀赫好香！\n3. 啦啦隊拚命追夢\n4. 她們不怕冷，怕跌！"
    },
    {
      "link": "https://tw.news.yahoo.com/super-junior%E9%8A%80%E8%B5%AB%E4%B8%BB%E6%8C%81%E7%AF%80%E7%9B%AE%E6%95%A3%E7%99%BC-%E7%86%9F%E6%82%89%E9%AB%94%E5%91%B3-%E5%A5%B3%E5%AD%A9%E6%B4%A9%E4%BB%96%E7%A7%81%E4%B8%8B%E6%9A%96%E8%88%89-091414079.html",
      "headLine": "Super Junior銀赫主持節目散發「熟悉體味」 女孩洩他私下暖舉",
      "publishDate": "2026-01-24T09:14:14.000Z",
      "source": "{\"@context\":\"http://schema.org\",\"@type\":\"NewsArticle\",\"mainEntityOfPage\":\"https://tw.news.yahoo.com/super-junior%E9%8A%80%E8%B5%AB%E4%B8%BB%E6%8C%81%E7%AF%80%E7%9B%AE%E6%95%A3%E7%99%BC-%E7%86%9F%E6%82%89%E9%AB%94%E5%91%B3-%E5%A5%B3%E5%AD%A9%E6%B4%A9%E4%BB%96%E7%A7%81%E4%B8%8B%E6%9A%96%E8%88%89-091414079.html\",\"headline\":\"Super Junior銀赫主持節目散發「熟悉體味」 女孩洩他私下暖舉\",\"datePublished\":\"2026-01-24T09:14:14.000Z\",\"dateModified\":\"2026-01-24T09:14:14.000Z\",\"keywords\":[\"緯來\",\"銀赫\"],\"description\":\"緯來選秀《宇宙啦啦隊》25位參賽成員，今（24日）和製作人B2（陳彥銘）、大胃王小慧、泰國娘娘等出席緯來電視網主辦的的公益二手市集「-1111 循寶夠物節」。一提到《宇宙啦啦隊》的主持人 Super Junior 銀赫，眾人有默契的說：「很香！」\",\"publisher\":{\"@type\":\"Organization\",\"name\":\"Yahoo奇摩新聞\",\"logo\":{\"@type\":\"ImageObject\",\"url\":\"https://s.yimg.com/cv/apiv2/twmobi/icon/yahoo_tw_logo_structuredata_20200630.png\",\"width\":136,\"height\":60}},\"author\":{\"@type\":\"Person\",\"name\":\"池宗玲\",\"url\":\"\",\"jobTitle\":\"\"},\"creator\":{\"@type\":\"Person\",\"name\":\"池宗玲\",\"url\":\"\",\"jobTitle\":\"\"},\"provider\":{\"@type\":\"Organization\",\"name\":\"中時新聞網\",\"url\":\"http://www.chinatimes.com\",\"logo\":{\"@type\":\"ImageObject\",\"width\":300,\"height\":50,\"url\":\"https://s.yimg.com/os/creatr-uploaded-images/2020-08/23410720-d6cf-11ea-be77-dd09959d161f\"}},\"image\":{\"@type\":\"ImageObject\",\"url\":\"https://s.yimg.com/ny/api/res/1.2/S94_OKeG.O9eqkYgi.lxAg--/YXBwaWQ9aGlnaGxhbmRlcjt3PTIwNDg7aD0xMzY0/https://media.zenfs.com/zh-tw/chinatimes.com.tw/d8fe5177499f5d065bfec2382adaaa66\",\"height\":682,\"width\":1024},\"thumbnailUrl\":\"https://s.yimg.com/ny/api/res/1.2/S94_OKeG.O9eqkYgi.lxAg--/YXBwaWQ9aGlnaGxhbmRlcjt3PTIwNDg7aD0xMzY0/https://media.zenfs.com/zh-tw/chinatimes.com.tw/d8fe5177499f5d065bfec2382adaaa66\"}",
      "content": "銀赫獨挑大梁，主持《宇宙啦啦隊》。（緯來提供）緯來選秀《宇宙啦啦隊》25位參賽成員，今（24日）和製作人B2（陳彥銘）、大胃王小慧、泰國娘娘等出席緯來電視網主辦的的公益二手市集「-1111 循寶夠物節」。一提到《宇宙啦啦隊》的主持人 Super Junior 銀赫，眾人有默契的說：「很香！」成員紀欣伶笑說，第一次靠近銀赫時，就聞到一股「很熟悉的香味」，「那是我平常很喜歡噴的香水品牌，忍不住直接問他是不是這個品牌的幾號香水，銀赫說對，沒想到真的猜中了」。廣告廣告成員們坦言，選秀競爭激烈，大家都給自己很多的壓力，尤其又是團隊比賽也怕影響其他人。她們也透露，銀赫私下相當貼心，訓練期間看到有人因選秀壓力落淚，銀赫會主動用中文安慰「不要哭」，讓大家瞬間被融化。泰國娘娘（左）、小慧24日出席公益二手市集。（緯來提供）大胃王小慧今在活動現場表演吃8支竹筒飯，猜到最靠近完食秒數的粉絲可以得到精美禮物。小慧透露，她私下食量不大，只有在工作狀態才會吃很多」，一番話讓人震驚。她也說，之前一整天吃太多，一度胖到 62 公斤，現在如果沒有拍攝，會盡量吃得養生一點，早餐就吃藍莓、優格跟堅果，「但份量依然是大胃王，一碗大概是五人份。」農曆年將到，最愛佛跳牆和煮到爛掉的芋頭小慧相當開心，霸氣的說：「年夜飯交給我消滅就好」，她也笑言，每年包給爸媽的紅包都會逐年增加。泰國娘娘分享第一次在台北過年的震撼經驗，直言：「台灣過年好無聊，路上都沒有人，也沒有紅色、金色的裝飾。」他更是幽默的開玩笑說，「公車司機都可以閉眼睛開車了，因為都沒有人」。他提到，泰國過年期間路上都充滿紅色、金色裝飾，熱鬧歡騰的氣氛和台灣差很多。而每年過年都會被規定要回家團聚的他也說，每次回泰國都在耍廢滑手機，很少安排外出活動。更多中時新聞網報導魏如萱穩交21歲男友愛得坦然入境帶國外加熱菸違法 罰5萬起跳鄧紫棋4月唱進台北大巨蛋",
      "imageUrl": "https://s.yimg.com/ny/api/res/1.2/QF6I9zOkatZtrHAw34ErNQ--/YXBwaWQ9aGlnaGxhbmRlcjt3PTk2MDtoPTYzOQ--/https://media.zenfs.com/zh-tw/chinatimes.com.tw/d8fe5177499f5d065bfec2382adaaa66",
      "imageProvider": "銀赫獨挑大梁，主持《宇宙啦啦隊》。（緯來提供）",
      "authorName": "池宗玲",
      "newsProvider": "中時新聞網",
      "suggestLine": "1. 銀赫超香！成員這樣說\n2. 大胃王私下食量嚇壞了\n3. 泰國娘娘：台年超無聊\n4. 銀赫「不要哭」融化她們"
    },
    {
      "link": "https://tw.news.yahoo.com/%E8%83%A1%E7%93%9C%E5%87%BA%E9%81%9340%E5%B9%B4%E7%BD%95%E8%A6%8B-%E8%85%BF%E8%BB%9F%E6%B1%82%E9%A5%92-%E5%87%BA%E8%81%B2%E6%8B%9C%E8%A8%97-%E4%BA%8B-091340656.html",
      "headLine": "胡瓜出道40年罕見「腿軟求饒」 出聲拜託一事",
      "publishDate": "2026-01-24T09:13:40.000Z",
      "source": "{\"@context\":\"http://schema.org\",\"@type\":\"NewsArticle\",\"mainEntityOfPage\":\"https://tw.news.yahoo.com/%E8%83%A1%E7%93%9C%E5%87%BA%E9%81%9340%E5%B9%B4%E7%BD%95%E8%A6%8B-%E8%85%BF%E8%BB%9F%E6%B1%82%E9%A5%92-%E5%87%BA%E8%81%B2%E6%8B%9C%E8%A8%97-%E4%BA%8B-091340656.html\",\"headline\":\"胡瓜出道40年罕見「腿軟求饒」 出聲拜託一事\",\"datePublished\":\"2026-01-24T09:13:40.000Z\",\"dateModified\":\"2026-01-24T09:13:40.000Z\",\"keywords\":[\"胡瓜\",\"啦啦隊\"],\"description\":\"「綜藝天王」胡瓜在YouTube頻道《下面一位》持續接受多樣全新挑戰。他在最新一集裡，一圓世新啦啦隊同學的夢想，讓大家將他舉起，體驗啦啦隊的高度，距離地面超高的距離讓胡瓜腿軟，拼命大喊：「趕快放我下來！」\",\"publisher\":{\"@type\":\"Organization\",\"name\":\"Yahoo奇摩新聞\",\"logo\":{\"@type\":\"ImageObject\",\"url\":\"https://s.yimg.com/cv/apiv2/twmobi/icon/yahoo_tw_logo_structuredata_20200630.png\",\"width\":136,\"height\":60}},\"author\":{\"@type\":\"Person\",\"name\":\"池宗玲\",\"url\":\"\",\"jobTitle\":\"\"},\"creator\":{\"@type\":\"Person\",\"name\":\"池宗玲\",\"url\":\"\",\"jobTitle\":\"\"},\"provider\":{\"@type\":\"Organization\",\"name\":\"中時新聞網\",\"url\":\"http://www.chinatimes.com\",\"logo\":{\"@type\":\"ImageObject\",\"width\":300,\"height\":50,\"url\":\"https://s.yimg.com/os/creatr-uploaded-images/2020-08/23410720-d6cf-11ea-be77-dd09959d161f\"}},\"image\":{\"@type\":\"ImageObject\",\"url\":\"https://s.yimg.com/ny/api/res/1.2/qHRm2dpnQc3_qKTJkMMcVA--/YXBwaWQ9aGlnaGxhbmRlcjt3PTIwNDg7aD0xMTU0/https://media.zenfs.com/ko/chinatimes.com.tw/b373a28b5fb1691c1078855b6242962c\",\"height\":577,\"width\":1024},\"thumbnailUrl\":\"https://s.yimg.com/ny/api/res/1.2/qHRm2dpnQc3_qKTJkMMcVA--/YXBwaWQ9aGlnaGxhbmRlcjt3PTIwNDg7aD0xMTU0/https://media.zenfs.com/ko/chinatimes.com.tw/b373a28b5fb1691c1078855b6242962c\"}",
      "content": "寵粉的胡瓜答應被啦啦隊抬起。（摘自YT）「綜藝天王」胡瓜在YouTube頻道《下面一位》持續接受多樣全新挑戰。他在最新一集裡，一圓世新啦啦隊同學的夢想，讓大家將他舉起，體驗啦啦隊的高度，距離地面超高的距離讓胡瓜腿軟，拼命大喊：「趕快放我下來！」胡瓜此次特別邀請奪得佳績的世新啦啦隊，他看同學們現場表演高空拋接等困難技術，默契良好，拋上空中的超高距離也讓胡瓜邊看邊驚呼。他本來想結束訪問，結果同學們提出想要抬起胡瓜的請求，他先找理由瘋狂推託，卻還是不敵同學們的熱情攻勢。廣告廣告胡瓜嚇到求饒。（摘自YT）他慰勞同學們的辛苦，特別請大家到小吃店飽餐一頓。他問起跳啦啦隊是否身上有許多損傷，沒想到同學們除了腰傷，還有開刀骨折，各種傷勢都讓胡瓜相當心疼。聊到當父母親看到多面金牌時，有沒有給予鼓勵？有位同學直接對著鏡頭向阿嬤喊話，希望阿嬤看到他和胡瓜同框能夠開心，氛圍相當溫暖。除了跟啦啦隊的互動，胡瓜也在文山區友人的介紹下品嚐麻油雞、美式餐廳等多樣美食，非常豐富的選擇，讓熱愛美食的胡瓜邊吃邊喊：「這樣吃下去可以嗎？完全是職業傷害！」更多中時新聞網報導轟小案大辦 全教總呼籲廢校事會議張懷秋二把手升格霸氣大哥許富凱行善送暖 首場攻蛋戰袍捐了",
      "imageUrl": "https://s.yimg.com/ny/api/res/1.2/cig.7HsHeAcjLbpej7h6gA--/YXBwaWQ9aGlnaGxhbmRlcjt3PTk2MDtoPTU0MQ--/https://media.zenfs.com/ko/chinatimes.com.tw/b373a28b5fb1691c1078855b6242962c",
      "imageProvider": "寵粉的胡瓜答應被啦啦隊抬起。（摘自YT）",
      "authorName": "池宗玲",
      "newsProvider": "中時新聞網",
      "suggestLine": "1. 胡瓜被抬高，嚇傻！\n2. 胡瓜腿軟尖叫啦！\n3. 啦啦隊舉起胡瓜！\n4. 天王被舉高高！"
    },
    {
      "link": "https://tw.news.yahoo.com/%E8%8E%8E%E8%8E%89%E8%B3%BD%E9%9A%86%E7%A7%80-%E6%89%8B-%E6%A4%85%E5%AD%90%E6%94%80%E5%B2%A9-%E5%B0%8D%E6%B1%BA%E9%9C%8D%E8%AB%BE%E5%BE%B7%E7%B6%B2%E7%8B%82%E8%AE%9A-%E8%B3%88%E6%B0%B8%E5%A9%95-090800582.html",
      "headLine": "莎莉賽隆秀一手「椅子攀岩」對決霍諾德網狂讚！賈永婕：有錢都請不到",
      "publishDate": "2026-01-24T09:08:00.000Z",
      "source": "{\"@context\":\"http://schema.org\",\"@type\":\"NewsArticle\",\"mainEntityOfPage\":\"https://tw.news.yahoo.com/%E8%8E%8E%E8%8E%89%E8%B3%BD%E9%9A%86%E7%A7%80-%E6%89%8B-%E6%A4%85%E5%AD%90%E6%94%80%E5%B2%A9-%E5%B0%8D%E6%B1%BA%E9%9C%8D%E8%AB%BE%E5%BE%B7%E7%B6%B2%E7%8B%82%E8%AE%9A-%E8%B3%88%E6%B0%B8%E5%A9%95-090800582.html\",\"headline\":\"莎莉賽隆秀一手「椅子攀岩」對決霍諾德網狂讚！賈永婕：有錢都請不到\",\"datePublished\":\"2026-01-24T09:08:00.000Z\",\"dateModified\":\"2026-01-24T09:08:00.000Z\",\"keywords\":[\"霍諾德\",\"莎莉賽隆\",\"台北101\",\"攀岩\",\"賈永婕\",\"Netflix\",\"Alex Honnold\"],\"description\":\"霍諾德原訂今（24）日挑戰徒手攀登台北101，不過因為天候不佳而延至明（25）日上午9點。有趣的是，奧斯卡影后莎莉賽隆得知霍諾德要進行的挑戰後，竟無預警向對方下戰帖，以「椅子攀岩」的方式一決高下；此舉除讓網友驚訝大讚「居然請到莎莉塞隆來宣傳，太不可思議」外，台北101董事長賈永婕也說「我也嚇傻了，真的是有錢都請不...\",\"publisher\":{\"@type\":\"Organization\",\"name\":\"Yahoo奇摩新聞\",\"logo\":{\"@type\":\"ImageObject\",\"url\":\"https://s.yimg.com/cv/apiv2/twmobi/icon/yahoo_tw_logo_structuredata_20200630.png\",\"width\":136,\"height\":60}},\"author\":{\"@type\":\"Person\",\"name\":\"三立新聞網\",\"url\":\"\",\"jobTitle\":\"\"},\"creator\":{\"@type\":\"Person\",\"name\":\"三立新聞網\",\"url\":\"\",\"jobTitle\":\"\"},\"provider\":{\"@type\":\"Organization\",\"name\":\"三立新聞網 setn.com\",\"url\":\"http://www.setn.com/\",\"logo\":{\"@type\":\"ImageObject\",\"width\":316,\"height\":48,\"url\":\"https://s.yimg.com/os/creatr-uploaded-images/2025-01/2c15e170-d866-11ef-97ff-6019437716ae\"}},\"image\":{\"@type\":\"ImageObject\",\"url\":\"https://s.yimg.com/ny/api/res/1.2/Ev1xhWu4YgWiY2MijaYXtw--/YXBwaWQ9aGlnaGxhbmRlcjt3PTI0MDA7aD0xMzUw/https://media.zenfs.com/ko/setn.com.tw/4ac11f85c0e49cdb4dc7a4d6f1c27c32\",\"height\":675,\"width\":1200},\"thumbnailUrl\":\"https://s.yimg.com/ny/api/res/1.2/Ev1xhWu4YgWiY2MijaYXtw--/YXBwaWQ9aGlnaGxhbmRlcjt3PTI0MDA7aD0xMzUw/https://media.zenfs.com/ko/setn.com.tw/4ac11f85c0e49cdb4dc7a4d6f1c27c32\"}",
      "content": "記者簡浩正／台北報導莎莉賽隆跟霍諾德展開「椅子攀岩」對決。（圖／翻攝自IG）美國攀岩大神霍諾德(Alex Honnold)原訂今（24）日挑戰徒手攀登台北101，不過因為天候不佳而延期至明（25）日上午9點，讓許多網友期待表現。有趣的是，奧斯卡影后莎莉賽隆（Charlize Theron）得知霍諾德要進行的挑戰後，竟無預警向對方下戰帖，以「椅子攀岩」的方式一決高下；此舉除讓網友驚訝大讚「居然請到莎莉賽隆來宣傳，太不可思議」外，台北101董事長賈永婕也說「我也嚇傻了，真的是有錢都請不到，超級開心的！」廣告廣告霍諾德徒手攀登台北101活動，原訂今日上午9點登場，可惜因天象不佳延期至明(25)日上午9點，上千名民眾接獲訊息紛紛散場，不過Netflix節目組仍在台北101前拍攝花絮，吸引百名粉絲圍觀，期盼霍諾德能夠現身跟大家見面。莎莉賽隆率先進行「椅子攀岩」挑戰。（圖／翻攝自IG）有趣的是，莎莉賽隆得知霍諾德要進行的挑戰後，竟無預警向對方下戰帖，以「椅子攀岩」的方式一決高下。從Netflix釋出的影片中可看到，莎莉賽隆表示聽聞霍諾德要爬101，正巧自己因為電影也有進行攀岩訓練，於是喊話霍諾德可以利用家中物品來挑戰，最終，莎莉賽隆率先使用椅子展示攀岩的技術。輪到霍諾德時，他也利用椅子完成挑戰。眾多網友期盼明天台北好天氣，讓霍諾德完成徒手攀台北101的挑戰。(圖／翻攝自賈永婕臉書）有網友就在脆（Threads）上發文說到，雖然今日因為天氣不好活動延期，「Netflix 居然可以請到莎莉賽隆來宣傳，真的太不可思議！從她口中說一句 Taipei 101 平常不知道要付多少宣傳費用，搞不好根本請不到！」直言Netflix 跟 Alex 這次真的把 Taipei 101推上一個新高度，這個活動的曝光效益真的非常廣大，希望明天一切順利。 🤞此發文也引來賈永婕回文，表示「我也嚇傻了，真的是有錢都請不到，超級開心的！」賈永婕也轉發該文說「哇塞是莎莉賽隆耶！好棒的影片喔。」更多三立新聞網報導說好放晴卻下雨？吳聖宇揭「氣象元兇」：週日信義區這時間沒雨「霸王級寒流」10週年！氣象署回顧超狂紀錄：日月潭下雪、全台宛如冰箱直擊／「他就在我眼前！」霍諾德徒手試爬101畫面曝 網友驚呼：大神來了獨家直擊／攀101倒數！粉絲合照霍諾德 超嗨大喊：今天值得了",
      "imageUrl": "https://s.yimg.com/ny/api/res/1.2/mwp5RgE6udQuh.KtorjdtQ--/YXBwaWQ9aGlnaGxhbmRlcjt3PTk2MDtoPTU0MA--/https://media.zenfs.com/ko/setn.com.tw/4ac11f85c0e49cdb4dc7a4d6f1c27c32",
      "imageProvider": "莎莉賽隆跟霍諾德展開「椅子攀岩」對決。（圖／翻攝自IG）",
      "authorName": "三立新聞網",
      "newsProvider": "三立新聞網 setn.com",
      "suggestLine": "1. 影后大神椅子戰！\n2. 莎莉賽隆挺101太狂！\n3. 霍諾德PK莎莉賽隆？\n4. 椅子攀岩世紀對決！"
    },
    {
      "link": "https://tw.news.yahoo.com/%E9%84%A7%E4%BD%B3%E8%8F%AF-%E5%85%AC%E4%B8%BB%E6%8A%B1%E8%83%A1%E6%96%87%E8%8B%B1-%E7%95%AB%E9%9D%A2%E6%9B%9D-%E4%BB%96%E5%97%A8%E5%96%8A-%E8%AE%8A%E5%A3%AF%E4%BA%86-090350678.html",
      "headLine": "鄧佳華「公主抱胡文英」畫面曝！他嗨喊：變壯了",
      "publishDate": "2026-01-24T09:03:50.000Z",
      "source": "{\"@context\":\"http://schema.org\",\"@type\":\"NewsArticle\",\"mainEntityOfPage\":\"https://tw.news.yahoo.com/%E9%84%A7%E4%BD%B3%E8%8F%AF-%E5%85%AC%E4%B8%BB%E6%8A%B1%E8%83%A1%E6%96%87%E8%8B%B1-%E7%95%AB%E9%9D%A2%E6%9B%9D-%E4%BB%96%E5%97%A8%E5%96%8A-%E8%AE%8A%E5%A3%AF%E4%BA%86-090350678.html\",\"headline\":\"鄧佳華「公主抱胡文英」畫面曝！他嗨喊：變壯了\",\"datePublished\":\"2026-01-24T09:03:50.000Z\",\"dateModified\":\"2026-01-24T09:03:50.000Z\",\"keywords\":[\"鄧佳華\",\"胡文英\"],\"description\":\"娛樂中心／楊佩怡報導網紅鄧佳華因在2023年任職髮廊期間，遭女設計師指控以手機偷拍其裙底畫面，經法院審理後，判處有期徒刑6個月，他於去（2025）年7月10日入監服刑，本月9日才刑滿重獲自由。近日攀岩大師艾力克斯．霍諾德（Alex Honnold）將挑戰徒手攀爬台北101，鄧佳華今（24）日也跑到101，合體美魔...\",\"publisher\":{\"@type\":\"Organization\",\"name\":\"Yahoo奇摩新聞\",\"logo\":{\"@type\":\"ImageObject\",\"url\":\"https://s.yimg.com/cv/apiv2/twmobi/icon/yahoo_tw_logo_structuredata_20200630.png\",\"width\":136,\"height\":60}},\"author\":{\"@type\":\"Person\",\"name\":\"民視新聞網\",\"url\":\"\",\"jobTitle\":\"\"},\"creator\":{\"@type\":\"Person\",\"name\":\"民視新聞網\",\"url\":\"\",\"jobTitle\":\"\"},\"provider\":{\"@type\":\"Organization\",\"name\":\"民視\",\"url\":\"https://www.ftvnews.com.tw/\",\"logo\":{\"@type\":\"ImageObject\",\"width\":300,\"height\":50,\"url\":\"https://s.yimg.com/os/creatr-uploaded-images/2020-09/cc0a4a40-fd32-11ea-bdce-e1b4e3c6229a\"}},\"image\":{\"@type\":\"ImageObject\",\"url\":\"https://s.yimg.com/ny/api/res/1.2/EKQ0kn13Zw1dcsFt.GVv4A--/YXBwaWQ9aGlnaGxhbmRlcjt3PTIwNDg7aD0xMTUy/https://media.zenfs.com/en/ftvn.com.tw/3d72eebbdaae1ba72fc207ae4e38da04\",\"height\":576,\"width\":1024},\"thumbnailUrl\":\"https://s.yimg.com/ny/api/res/1.2/EKQ0kn13Zw1dcsFt.GVv4A--/YXBwaWQ9aGlnaGxhbmRlcjt3PTIwNDg7aD0xMTUy/https://media.zenfs.com/en/ftvn.com.tw/3d72eebbdaae1ba72fc207ae4e38da04\"}",
      "content": "娛樂中心／楊佩怡報導網紅鄧佳華因在2023年任職髮廊期間，遭女設計師指控以手機偷拍其裙底畫面，經法院審理後，判處有期徒刑6個月，他於去（2025）年7月10日入監服刑，本月9日才刑滿重獲自由。近日攀岩大師艾力克斯．霍諾德（Alex Honnold）將挑戰徒手攀爬台北101，鄧佳華今（24）日也跑到101，合體美魔女胡文英，並一把將她抱起轉一圈，過程中還不斷嗨喊「變壯了！」，甚至稱自己也可以「徒手爬台北 101」，引發網友熱議。廣告廣告鄧佳華剛出獄變壯了？公主抱「比基尼胡文英」轉1圈嗨喊：可以徒手爬101鄧佳華（後）驚喜合體美魔女胡文英（前），還將對方一把抱起。（圖／翻攝自IG＠鄧佳華）鄧佳華今（24）日在IG曬出一段影片，女主角竟是「美魔女」胡文英，畫面中可見，胡文英身穿一件酒紅色Bra，性感的身材線條一覽無疑；下身則穿著極短褲和長襪，露出一大截纖細長腿。而影片中的鄧佳華則試圖展現自己的力量，他蹲下身子，用「公主抱」的方式將胡文英抱起。鄧佳華剛出獄變壯了？公主抱「比基尼胡文英」轉1圈嗨喊：可以徒手爬101鄧佳華在影片中不斷稱自己變壯了，連胡文英都認證。（圖／翻攝自IG＠鄧佳華）雖然過程中看起來稍微有些吃力，但他成功地將胡文英抬離地面。抱起胡文英後，鄧佳華顯得非常有自信，對著鏡頭表示自己「真的變厲害了」，甚至開玩笑說現在的體力足以讓他「徒手爬上台北 101」。胡文英在鄧佳華懷中大方配合，並對著鏡頭比出V字手勢。隨後，鄧佳華還抱著她原地轉了一圈，胡文英驚呼：「真的有變壯！」。胡文英被放下後，稱讚鄧佳華變得「不一樣了有壯」，而鄧佳華則開心的對著鏡頭豎起大拇指。畫面曝光後，引來不少網友表示「老大好帥」、「佳華大哥好像抱了不少妹」、「羨慕」、「美魔女很熟」。原文出處：鄧佳華剛出獄變壯漢？公主抱「比基尼胡文英」轉1圈嗨喊：可以徒手爬101更多民視新聞報導前暗黑天后蒼井空突表態！嗨喊「我喜歡中國」遭罵爆「X形」女老師激戰片外流！大尺度課程吸金1億X形老師賣「無碼實戰片」海撈1憶！前員工再抖大尺度黑料",
      "imageUrl": "https://s.yimg.com/ny/api/res/1.2/2_YD7g2pvKpQ4SJgjbKZvA--/YXBwaWQ9aGlnaGxhbmRlcjt3PTk2MDtoPTU0MA--/https://media.zenfs.com/en/ftvn.com.tw/3d72eebbdaae1ba72fc207ae4e38da04",
      "imageProvider": "鄧佳華剛出獄變壯了？公主抱「比基尼胡文英」轉1圈嗨喊：可以徒手爬101",
      "authorName": "民視新聞網",
      "newsProvider": "民視",
      "suggestLine": "1. 佳華出獄變壯？公主抱胡文英！\n2. 鄧佳華：我能徒手爬101！\n3. 出獄鄧佳華，抱美魔女轉圈！\n4. 鄧佳華變壯！嗨喊：能爬101！"
    },
    {
      "link": "https://tw.news.yahoo.com/%E6%98%8E%E6%98%9F%E8%A3%BD%E4%BD%9C%E5%85%AC%E5%8F%B8-%E5%B9%95%E5%BE%8C%E5%A4%A7%E6%94%A4%E7%89%8C-%E7%81%AB%E8%8A%B1%E5%9B%9B%E5%B0%84%E5%89%B5%E6%84%8F%E5%85%A8%E9%96%8B-090200131.html",
      "headLine": "《明星製作公司》幕後大攤牌 火花四射創意全開",
      "publishDate": "2026-01-24T09:02:00.000Z",
      "source": "{\"@context\":\"http://schema.org\",\"@type\":\"NewsArticle\",\"mainEntityOfPage\":\"https://tw.news.yahoo.com/%E6%98%8E%E6%98%9F%E8%A3%BD%E4%BD%9C%E5%85%AC%E5%8F%B8-%E5%B9%95%E5%BE%8C%E5%A4%A7%E6%94%A4%E7%89%8C-%E7%81%AB%E8%8A%B1%E5%9B%9B%E5%B0%84%E5%89%B5%E6%84%8F%E5%85%A8%E9%96%8B-090200131.html\",\"headline\":\"《明星製作公司》幕後大攤牌 火花四射創意全開\",\"datePublished\":\"2026-01-24T09:02:00.000Z\",\"dateModified\":\"2026-01-24T09:02:00.000Z\",\"keywords\":[\"楊銘威\",\"曾莞婷\",\"Lulu 黃路梓茵\",\"TVBS\",\"苗可麗\",\"黃偉晉\",\"陳漢典\"],\"description\":\"TVBS實境節目《明星製作公司》首度公開從未曝光的幕後過程，六位成員曾莞婷、陳漢典、楊銘威、Lulu 黃路梓茵、黃偉晉與風田，挑戰高難度任務「短劇製作」，不只創意全開，拍攝現場更一度火花四射，真實呈現明星從零開始做內容的血汗日常。 短劇《阿珠與阿花》由曾莞婷主動攬下製作人重任，憑藉多年人脈成功邀請謝承均、苗可麗友...\",\"publisher\":{\"@type\":\"Organization\",\"name\":\"Yahoo奇摩新聞\",\"logo\":{\"@type\":\"ImageObject\",\"url\":\"https://s.yimg.com/cv/apiv2/twmobi/icon/yahoo_tw_logo_structuredata_20200630.png\",\"width\":136,\"height\":60}},\"author\":{\"@type\":\"Person\",\"name\":\"青年日報\",\"url\":\"\",\"jobTitle\":\"\"},\"creator\":{\"@type\":\"Person\",\"name\":\"青年日報\",\"url\":\"\",\"jobTitle\":\"\"},\"provider\":{\"@type\":\"Organization\",\"name\":\"青年日報\",\"url\":\"https://www.ydn.com.tw/\",\"logo\":{\"@type\":\"ImageObject\",\"width\":336,\"height\":90,\"url\":\"https://s.yimg.com/os/creatr-uploaded-images/2025-12/5dcecbf0-d419-11f0-bfef-ed0eef1617dc\"}},\"image\":{\"@type\":\"ImageObject\",\"url\":\"https://s.yimg.com/ny/api/res/1.2/3fq0dR2JdzEGBz2dpPkHTw--/YXBwaWQ9aGlnaGxhbmRlcjt3PTI0MDA7aD0xNjAw/https://media.zenfs.com/ko/youthdailynews_517/f1e40fe1e99d686c4ab0cc8d6c723584\",\"height\":800,\"width\":1200},\"thumbnailUrl\":\"https://s.yimg.com/ny/api/res/1.2/3fq0dR2JdzEGBz2dpPkHTw--/YXBwaWQ9aGlnaGxhbmRlcjt3PTI0MDA7aD0xNjAw/https://media.zenfs.com/ko/youthdailynews_517/f1e40fe1e99d686c4ab0cc8d6c723584\"}",
      "content": "記者周毓洵／臺北報導TVBS實境節目《明星製作公司》首度公開從未曝光的幕後過程，六位成員曾莞婷、陳漢典、楊銘威、Lulu 黃路梓茵、黃偉晉與風田，挑戰高難度任務「短劇製作」，不只創意全開，拍攝現場更一度火花四射，真實呈現明星從零開始做內容的血汗日常。短劇《阿珠與阿花》由曾莞婷主動攬下製作人重任，憑藉多年人脈成功邀請謝承均、苗可麗友情客串，讓作品瞬間升級；Lulu 也出手加碼，邀請玖壹壹成員洋蔥驚喜現身，卡司曝光後讓全場士氣大振。廣告廣告導演則由楊銘威擔任，目標神還原八點檔經典橋段，沒想到排戲時卻先上演一場「真實八點檔」。曾莞婷認為八點檔必須大量特寫、情緒拉滿才能抓住觀眾；楊銘威則擔心畫面過碎、節奏被打亂，兩人各持立場，現場氣氛一度僵住，連工作人員都不敢插話。關鍵時刻，楊銘威選擇直接試拍，用畫面說服大家，最終也讓曾莞婷點頭認同，這場製作人與導演的攻防戰才順利落幕。事後楊銘威緩頰表示，其實討論氣氛很好，拍攝過程笑聲不斷，還把成品傳給好友柯震東「驗收」，對方看完直接大笑，直呼真的很鬧。誇張又充滿反差的演出，加上楊銘威臨場即興的加戲設計，也讓苗可麗全程拍手叫好，笑說從頭笑到尾，「如果每天都能在這樣的環境工作，真的會很快樂，能讓觀眾放鬆看喜劇，也算是功德一件。」謝承均也大讚大家專業度滿分，完全不需要指導，還期待下次再來客串。同時身兼製片與演員的黃偉晉則笑虧楊銘威的分鏡圖「很像國小聯絡簿」，但也認真補充：「他其實非常清楚自己要拍什麼，還能依現場狀況精準加戲，完全不會讓演員卡關，而且超會給情緒價值。」另一位製片風田則包辦場勘、道具與劇組飲食，忙到不可開交，卻忍不住自嘲：「沒想到只是準備幾個人的便當就可以累成這樣，而且我這麼努力，卻都沒有人看到。」一句話道出幕後工作者的心聲。《明星製作公司》曾莞婷（右三）、陳漢典（左一）、楊銘威（左二）、Lulu黃路梓茵（右二）、黃偉晉（左三）與風田（右一）挑戰「短劇製作」。（TVBS提供）《明星製作公司》第二集短劇《阿珠與阿花》曾莞婷主動攬下製作人重任。（TVBS提供）《明星製作公司》風田（左）與偉晉（右）擔任製片一手包辦劇組大小事。（TVBS提供）《明星製作公司》苗可麗（左起）、陳漢典與Lulu拍攝短劇。（TVBS提供）",
      "imageUrl": "https://s.yimg.com/ny/api/res/1.2/D2mHdqJ7c.zrh8M0NHFgOA--/YXBwaWQ9aGlnaGxhbmRlcjt3PTk2MDtoPTY0MA--/https://media.zenfs.com/ko/youthdailynews_517/f1e40fe1e99d686c4ab0cc8d6c723584",
      "imageProvider": null,
      "authorName": "青年日報",
      "newsProvider": "青年日報",
      "suggestLine": "1. 明星互槓！幕後火花四射。\n2. 揭秘明星血汗！製作內幕公開。\n3. 苗可麗讚爆！大咖助陣升級。\n4. 柯震東大笑！明星短劇鬧翻天。"
    },
    {
      "link": "https://tw.news.yahoo.com/101%E5%A4%A7%E6%A8%93%E5%85%88%E7%B7%A9%E7%B7%A9-%E8%89%BE%E5%8A%9B%E5%85%8B%E6%96%AF%E6%94%B9%E7%88%AC%E8%B1%A1%E5%B1%B1%E4%BA%86-%E7%B6%B2%E7%BE%A8%E7%82%B8-%E7%8F%BE%E5%9C%A8%E5%8E%BB%E4%BE%86%E5%BE%97%E5%8F%8A%E5%97%8E-085810426.html",
      "headLine": "101大樓先緩緩！艾力克斯改爬象山了 網羨炸：現在去來得及嗎",
      "publishDate": "2026-01-24T08:58:10.000Z",
      "source": "{\"@context\":\"http://schema.org\",\"@type\":\"NewsArticle\",\"mainEntityOfPage\":\"https://tw.news.yahoo.com/101%E5%A4%A7%E6%A8%93%E5%85%88%E7%B7%A9%E7%B7%A9-%E8%89%BE%E5%8A%9B%E5%85%8B%E6%96%AF%E6%94%B9%E7%88%AC%E8%B1%A1%E5%B1%B1%E4%BA%86-%E7%B6%B2%E7%BE%A8%E7%82%B8-%E7%8F%BE%E5%9C%A8%E5%8E%BB%E4%BE%86%E5%BE%97%E5%8F%8A%E5%97%8E-085810426.html\",\"headline\":\"101大樓先緩緩！艾力克斯改爬象山了 網羨炸：現在去來得及嗎\",\"datePublished\":\"2026-01-24T08:58:10.000Z\",\"dateModified\":\"2026-01-24T08:58:10.000Z\",\"keywords\":[\"艾力克斯\",\"台北101大樓\",\"Ａlex Honnold\",\"象山\"],\"description\":\"美國攀岩好手艾力克斯（Ａlex Honnold）原定在今（24日）征服台北101大樓，無奈天公不作美，被寒冷的雨水澆熄計畫，只好延到明天舉辦。艾力克斯也透露會改去附近健行，結果真的被網友在象山巧遇，引起熱烈討論。\",\"publisher\":{\"@type\":\"Organization\",\"name\":\"Yahoo奇摩新聞\",\"logo\":{\"@type\":\"ImageObject\",\"url\":\"https://s.yimg.com/cv/apiv2/twmobi/icon/yahoo_tw_logo_structuredata_20200630.png\",\"width\":136,\"height\":60}},\"author\":{\"@type\":\"Person\",\"name\":\"詹鎰睿\",\"url\":\"\",\"jobTitle\":\"\"},\"creator\":{\"@type\":\"Person\",\"name\":\"詹鎰睿\",\"url\":\"\",\"jobTitle\":\"\"},\"provider\":{\"@type\":\"Organization\",\"name\":\"中時新聞網\",\"url\":\"http://www.chinatimes.com\",\"logo\":{\"@type\":\"ImageObject\",\"width\":300,\"height\":50,\"url\":\"https://s.yimg.com/os/creatr-uploaded-images/2020-08/23410720-d6cf-11ea-be77-dd09959d161f\"}},\"image\":{\"@type\":\"ImageObject\",\"url\":\"https://s.yimg.com/ny/api/res/1.2/E6wdhQCiqjr7r6dE95PLCA--/YXBwaWQ9aGlnaGxhbmRlcjt3PTIwNDg7aD0xMzQw/https://media.zenfs.com/en/chinatimes.com.tw/ca8ddc0b4fa27b8152dfa3ae37be2c09\",\"height\":670,\"width\":1024},\"thumbnailUrl\":\"https://s.yimg.com/ny/api/res/1.2/E6wdhQCiqjr7r6dE95PLCA--/YXBwaWQ9aGlnaGxhbmRlcjt3PTIwNDg7aD0xMzQw/https://media.zenfs.com/en/chinatimes.com.tw/ca8ddc0b4fa27b8152dfa3ae37be2c09\"}",
      "content": "艾力克斯取消原定的徒手攀爬101計畫，改去象山健行，結果真的被網友巧遇到。（圖／IG@alexhonnold、Netflix提供）美國攀岩好手艾力克斯（Ａlex Honnold）原定在今（24日）征服台北101大樓，無奈天公不作美，被寒冷的雨水澆熄計畫，只好延到明天舉辦。艾力克斯也透露會改去附近健行，結果真的被網友在象山巧遇，引起熱烈討論。艾力克斯一早透過社群平台和大家宣布，取消今天的爬101的挑戰，「嘿，我是Alex，我現在人在雨下得很大的台北。 呃，很遺憾今天因為下雨的關係，我沒辦法去爬101」。雖然被大雨澆熄計劃，但艾力克斯不忘稱讚台北市是一座美麗的城市，並透露等下打算去附近健行，好好度過一天，也請大家持續關注，感謝大家的支持。廣告廣告沒想到影片發布幾個鐘頭後，就有網友幸運在象山遇到正在爬山的艾力克斯。貼文照片曝光後，立刻吸引上萬名網友瀏覽，大家紛紛留言表示，「感覺整個信義區都是Alex的伸展台...」、「這個男人去爬象山對他來說應該只是夢遊等級」、「他應該不用走步道，從山壁爬上去哈哈哈」、「羨慕了，現在去象山來得及嗎？」   在 Threads 查看其實為了能親眼見證艾力克斯徒手攀上101大樓的壯舉，除了台灣，還有許多來自其他國家的粉絲慕名而來，特地安排行程來到台灣。無奈天公不作美，讓眾人撲了空。不過大家情緒依舊高昂，希望艾力克斯平平安安，成功完成這項艱困的挑戰，紛紛在現場或是透過社群上給予支持和鼓勵。更多中時新聞網報導動力火車攻蛋先「閉嘴」餓到哀哀叫金世正脫浴袍炫腹 撂中文喊想你們NBA》勇士添傷兵又吞敗 快艇險勝湖人",
      "imageUrl": "https://s.yimg.com/ny/api/res/1.2/lt6jJML5YD1M9qG5jDWYNw--/YXBwaWQ9aGlnaGxhbmRlcjt3PTk2MDtoPTYyOA--/https://media.zenfs.com/en/chinatimes.com.tw/ca8ddc0b4fa27b8152dfa3ae37be2c09",
      "imageProvider": "艾力克斯取消原定的徒手攀爬101計畫，改去象山健行，結果真的被網友巧遇到。（圖／IG@alexhonnold、Netflix提供）",
      "authorName": "詹鎰睿",
      "newsProvider": "中時新聞網",
      "suggestLine": "1. 象山捕獲野生艾力克斯！\n2. 101不爬了，他改爬象山！\n3. 艾力克斯驚現象山！\n4. 雨淋101，他轉攻象山！"
    },
    {
      "link": "https://tw.news.yahoo.com/%E6%9E%97%E7%BE%8E%E8%B2%9E-%E4%B8%8D%E5%86%8D%E5%A7%94%E5%B1%88-%E7%8B%A0%E6%96%AC20%E5%A4%9A%E5%B9%B4%E6%83%85%E7%B5%B2-%E5%AD%AB%E8%88%88%E5%BE%A9%E5%90%88%E5%A5%B3%E5%AF%8C%E5%95%86-%E7%94%9C%E8%9C%9C%E5%90%8C%E6%A1%86%E5%96%8A-085100273.html",
      "headLine": "林美貞「不再委屈」狠斬20多年情絲 孫興復合女富商！甜蜜同框喊「愛人」放閃",
      "publishDate": "2026-01-24T08:51:00.000Z",
      "source": "{\"@context\":\"http://schema.org\",\"@type\":\"NewsArticle\",\"mainEntityOfPage\":\"https://tw.news.yahoo.com/%E6%9E%97%E7%BE%8E%E8%B2%9E-%E4%B8%8D%E5%86%8D%E5%A7%94%E5%B1%88-%E7%8B%A0%E6%96%AC20%E5%A4%9A%E5%B9%B4%E6%83%85%E7%B5%B2-%E5%AD%AB%E8%88%88%E5%BE%A9%E5%90%88%E5%A5%B3%E5%AF%8C%E5%95%86-%E7%94%9C%E8%9C%9C%E5%90%8C%E6%A1%86%E5%96%8A-085100273.html\",\"headline\":\"林美貞「不再委屈」狠斬20多年情絲 孫興復合女富商！甜蜜同框喊「愛人」放閃\",\"datePublished\":\"2026-01-24T08:51:00.000Z\",\"dateModified\":\"2026-01-24T08:51:00.000Z\",\"keywords\":[\"林美貞\",\"Oliver\",\"孫興\"],\"description\":\"55歲的林美貞與前夫孫興情纏20多年、三度分合，去年4月宣告「畢業了」正式斷開這段關係，對於原因不願多說，外界猜測孫興在與林美貞復合後，與女富商「燕子（Oliver）」並沒有斷乾淨，才讓被劈腿的林美貞心死、不再回頭。而孫興在社群上也不藏了，與Oliver多次大方同框曬恩愛。\",\"publisher\":{\"@type\":\"Organization\",\"name\":\"Yahoo奇摩新聞\",\"logo\":{\"@type\":\"ImageObject\",\"url\":\"https://s.yimg.com/cv/apiv2/twmobi/icon/yahoo_tw_logo_structuredata_20200630.png\",\"width\":136,\"height\":60}},\"author\":{\"@type\":\"Person\",\"name\":\"鏡報 杜沛學\",\"url\":\"\",\"jobTitle\":\"\"},\"creator\":{\"@type\":\"Person\",\"name\":\"鏡報 杜沛學\",\"url\":\"\",\"jobTitle\":\"\"},\"provider\":{\"@type\":\"Organization\",\"name\":\"鏡報\",\"url\":\"https://www.mirrordaily.news/\",\"logo\":{\"@type\":\"ImageObject\",\"width\":288,\"height\":48,\"url\":\"https://s.yimg.com/os/creatr-uploaded-images/2025-06/a90d5820-45d5-11f0-b31b-a3eb98b8e54f\"}},\"image\":{\"@type\":\"ImageObject\",\"url\":\"https://s.yimg.com/ny/api/res/1.2/oJQ_V3Tx0ifkXI620kSyhA--/YXBwaWQ9aGlnaGxhbmRlcjt3PTI0MDA7aD0xNjAw/https://media.zenfs.com/ko/mirrordaily_390/9ac7b1eb53d1842c0c88e253b962148e\",\"height\":800,\"width\":1200},\"thumbnailUrl\":\"https://s.yimg.com/ny/api/res/1.2/oJQ_V3Tx0ifkXI620kSyhA--/YXBwaWQ9aGlnaGxhbmRlcjt3PTI0MDA7aD0xNjAw/https://media.zenfs.com/ko/mirrordaily_390/9ac7b1eb53d1842c0c88e253b962148e\"}",
      "content": "林美貞（右）切割關係後，孫興（左）大方與Oliver曬恩愛。翻攝林美貞臉書、孫興小紅書55歲的林美貞與前夫孫興情纏20多年、三度分合，去年4月宣告「畢業了」正式斷開這段關係，對於原因不願多說，外界猜測孫興在與林美貞復合後，與女富商「燕子（Oliver）」並沒有斷乾淨，才讓被劈腿的林美貞心死、不再回頭。而孫興在社群上也不藏了，與Oliver多次大方同框曬恩愛。林美貞與孫興2001年結婚，因男方爆出軌，2007年離婚；兩人後又於2015年再婚，但也離婚收場。前年底兩人同遊泰國，爆出再度復合。但去年4月，林美貞發文：「我，林美貞，已正式簽字離婚，結束與孫興先生二十幾年的婚姻和所謂的家人關係，從今以後，他的任何行為，都與我和兒子無關！」廣告廣告林美貞發「畢業文」切割孫興。翻攝林美貞臉書林美貞怒嗆「犯錯」 孫興拉女富商到處旅遊文中林美貞還提到：「這一次，我不再妥協、不再委屈、也不願意在沈默中否定自己的感受！無論過去有多少愛與傷痛、多少欺騙與不堪，到此為止！過去的種種，不再定義我、束縛我。因此我也不再為別人犯下的錯誤承擔責任！」被林美貞正式切割後，孫興對於復合Oliver也不藏了，去年夏天就在社群開始與Oliver大方曬恩愛，兩人到處旅遊，騎駱駝、露營、到三亞參加朋友婚禮，Oliver也在影片中稱呼孫興為「愛人」。而林美貞宣布離婚後出席記者會，對於這段關係也不願再多談。Oliver（左）在影片中稱呼孫興為「愛人」。翻攝孫興小紅書回到原文更多鏡報報導35歲BL劇男星管麟宣布登記結婚！日期藏甜蜜紀念 小3歲妻備孕計劃曝光陳漢典、Lulu大婚！郁方搶先送自家珠寶 「黃鑽不能太大顆」超貼心原因曝光小女婿無預警驟逝！賴佩霞悲痛喊：我憤怒 揭「靈性對話」梳理混亂心情勇消魂斷火場身後留「小四獨生女」…分隊長掩面痛哭：孩子怎麼辦？",
      "imageUrl": "https://s.yimg.com/ny/api/res/1.2/ILM7SK.a_ORq4lO6ZxfxWg--/YXBwaWQ9aGlnaGxhbmRlcjt3PTk2MDtoPTY0MA--/https://media.zenfs.com/ko/mirrordaily_390/9ac7b1eb53d1842c0c88e253b962148e",
      "imageProvider": "林美貞（右）切割關係後，孫興（左）大方與Oliver曬恩愛。翻攝林美貞臉書、孫興小紅書",
      "authorName": "鏡報 杜沛學",
      "newsProvider": "鏡報",
      "suggestLine": "好的，這則新聞的引導句子，提供以下 4 句給您參考：\n\n1.  情纏20年，她心死！\n2.  孫興新歡，不藏了！\n3.  林美貞怒斬20年情！\n4.  情斷切割，他曬愛！"
    },
    {
      "link": "https://tw.news.yahoo.com/%E8%87%AA%E5%B8%B6%E8%B2%B4%E4%BA%BA%E9%81%8B-%E9%80%993%E5%A4%A7%E6%98%9F%E5%BA%A7%E5%A5%B3-%E5%A9%9A%E5%89%8D%E6%97%BA%E8%87%AA%E5%B7%B1-%E5%A9%9A%E5%BE%8C%E6%9B%B4%E6%97%BA%E5%AE%B6%E5%BA%AD-070011243.html",
      "headLine": "自帶貴人運！這3大星座女「婚前旺自己」、婚後更旺家庭",
      "publishDate": "2026-01-24T07:00:11.000Z",
      "source": "{\"@context\":\"http://schema.org\",\"@type\":\"NewsArticle\",\"mainEntityOfPage\":\"https://tw.news.yahoo.com/%E8%87%AA%E5%B8%B6%E8%B2%B4%E4%BA%BA%E9%81%8B-%E9%80%993%E5%A4%A7%E6%98%9F%E5%BA%A7%E5%A5%B3-%E5%A9%9A%E5%89%8D%E6%97%BA%E8%87%AA%E5%B7%B1-%E5%A9%9A%E5%BE%8C%E6%9B%B4%E6%97%BA%E5%AE%B6%E5%BA%AD-070011243.html\",\"headline\":\"自帶貴人運！這3大星座女「婚前旺自己」、婚後更旺家庭\",\"datePublished\":\"2026-01-24T07:00:11.000Z\",\"dateModified\":\"2026-01-24T07:00:11.000Z\",\"keywords\":[],\"description\":\"有些女生在不同人生階段，都能把生活經營得有條有理。她們在婚前能靠自己累積人脈與實力，進入婚姻後，也常在伴侶身邊發揮穩定作用，走到哪裡都容易遇到願意幫忙的人。以下這3個星座女，正是這樣的類型。\",\"publisher\":{\"@type\":\"Organization\",\"name\":\"Yahoo奇摩新聞\",\"logo\":{\"@type\":\"ImageObject\",\"url\":\"https://s.yimg.com/cv/apiv2/twmobi/icon/yahoo_tw_logo_structuredata_20200630.png\",\"width\":136,\"height\":60}},\"author\":{\"@type\":\"Person\",\"name\":\"李子晴 綜合報導\",\"url\":\"\",\"jobTitle\":\"\"},\"creator\":{\"@type\":\"Person\",\"name\":\"李子晴 綜合報導\",\"url\":\"\",\"jobTitle\":\"\"},\"provider\":{\"@type\":\"Organization\",\"name\":\"姊妹淘\",\"url\":\"https://babyou.me/\",\"logo\":{\"@type\":\"ImageObject\",\"width\":1250,\"height\":209,\"url\":\"https://s.yimg.com/os/creatr-uploaded-images/2020-10/341b1ab0-06de-11eb-bf9f-767a2794e04a\"}},\"image\":{\"@type\":\"ImageObject\",\"url\":\"https://s.yimg.com/ny/api/res/1.2/rKjuTjMi5fjS_DSTFgFRfw--/YXBwaWQ9aGlnaGxhbmRlcjt3PTk2MDtoPTE0Mzk-/https://media.zenfs.com/ko/babyou_nownews_com_883/fe7a4a92b8aa8a1fd1bcf2f695c22c96\",\"height\":1024,\"width\":683},\"thumbnailUrl\":\"https://s.yimg.com/ny/api/res/1.2/rKjuTjMi5fjS_DSTFgFRfw--/YXBwaWQ9aGlnaGxhbmRlcjt3PTk2MDtoPTE0Mzk-/https://media.zenfs.com/ko/babyou_nownews_com_883/fe7a4a92b8aa8a1fd1bcf2f695c22c96\"}",
      "content": "有些女生在不同人生階段，都能把生活經營得有條有理。她們在婚前能靠自己累積人脈與實力，進入婚姻後，也常在伴侶身邊發揮穩定作用，走到哪裡都容易遇到願意幫忙的人。以下這3個星座女，正是這樣的類型。射手女：行動力強，社交圈自然擴大射手女個性樂觀，做事直接，婚前就展現出不小的行動力。她們喜歡嘗試新事物，不把自己侷限在固定圈子，社交場合來往頻繁，也因此累積不少人脈與經驗。無論在工作或生活上，都能靠主動出擊找到機會。廣告廣告進入婚姻後，射手女依舊保持這樣的節奏。當伴侶遇到低潮時，她們常用輕鬆的態度陪對方走過，氣氛不至於太沉重。她們原本建立的人際關係，也可能在不經意間，為另一半帶來新的接觸機會。摩羯女：步調穩定，習慣為未來做準備摩羯女做事一向重視規劃。婚前，她們把重心放在累積實力與經驗，不追求短期成果，而是一步步把基礎打好，生活與工作多半走得穩健。婚後，摩羯女仍然維持這樣的做事方式。她們會把家庭視為需要長期經營的事情，同時也不忽略自身成長，並在規畫過程中，將伴侶的發展一併納入考量。因為做事可靠、態度務實，摩羯女往往能獲得前輩或合作對象的信任，在需要時得到實際幫助。處女女：重視細節，習慣把事情想周全處女座女生對自己要求高，婚前就不斷學習、累積能力，生活中的大小事也會事先安排好。這樣的習慣，讓她們在單身時期就建立起穩定的生活節奏。婚後，處女女的細心特質更明顯。她們能把家中事務處理妥當，也常在伴侶遇到問題時，從旁觀察並提出具體建議，協助對方調整方向。因為做事謹慎、考量全面，處女女在朋友與工作圈中容易建立好口碑，遇到需要協助的時刻，也較容易有人願意伸出援手。 延伸閱讀2026年好運降臨！這4星座女迎來命運翻轉 第1名突破瓶頸展翅高飛天生氣場超強！3星座女自帶霸氣，走到哪都很難被忽視",
      "imageUrl": "https://s.yimg.com/ny/api/res/1.2/rKjuTjMi5fjS_DSTFgFRfw--/YXBwaWQ9aGlnaGxhbmRlcjt3PTk2MDtoPTE0Mzk-/https://media.zenfs.com/ko/babyou_nownews_com_883/fe7a4a92b8aa8a1fd1bcf2f695c22c96",
      "imageProvider": null,
      "authorName": "李子晴 綜合報導",
      "newsProvider": "姊妹淘",
      "suggestLine": ""
    }
  ],
  "generatedAt": "2026-01-24T09:59:41.629Z"
}